Workbook
Name \0: #REF!
Name \A: #REF!
Name \asdf: #REF!
Name \B: #REF!
Name \C: #REF!
Name \d: #REF!
Name \E: #REF!
Name \F: #REF!
Name \Fa: #REF!
Name \G: #REF!
Name \H: #REF!
Name \I: #REF!
Name \K: #REF!
Name \l: #REF!
Name \M: #REF!
Name \n: #REF!
Name \P: #REF!
Name \Q: #REF!
Name \R: #REF!
Name \S: #REF!
Name \T: #REF!
Name \U: #REF!
Name \V: #REF!
Name \W: #REF!
Name \X: #REF!
Name \Y: #REF!
Name \Z: #REF!
Name _: #REF!
Name __________cmp1: #REF!
Name __________glf1: #REF!
Name __________hrh1: #REF!
Name __________hrm1: #REF!
Name __________kit61: #REF!
Name __________lbh1: #REF!
Name __________lbm1: #REF!
Name __________pkh1: #REF!
Name __________pkm1: #REF!
Name __________rsh1: #REF!
Name __________rsm1: #REF!
Name __________rst1: #REF!
Name __________rst2: #REF!
Name __________rst3: #REF!
Name __________rst4: #REF!
Name __________rt1: #REF!
Name __________rt2: #REF!
Name __________rt3: #REF!
Name __________rt4: #REF!
Name __________rtm4: #REF!
Name __________sph1: #REF!
Name __________spm1: #REF!
Name __________tnh1: #REF!
Name __________tnm1: #REF!
Name _________key1: #REF!
Name _________key2: #REF!
Name ________agc2: #REF!
Name ________agc3: #REF!
Name ________jo2: {#N/A,#N/A,FALSE,"DCF-COM";#N/A,#N/A,FALSE,"VAC-COM"}
Name ________jo3: {"CASHFLOW",#N/A,FALSE,"Northpointe"}
Name ________jo4: {#N/A,#N/A,FALSE,"SHEET1";#N/A,#N/A,FALSE,"SHEET2";#N/A,#N/A,FALSE,"SHEET3";#N/A,#N/A,FALSE,"SHEET4"}
Name ________key1: #REF!

Sheet llm_README
A1: llm_README - Workbook Documentation
A3: WORKBOOK SUMMARY
A4: Business Purpose: | B4: Construction/Real Estate project budget management system. Tracks job setup, forecasts, budgets, vendor details, tenant estimates, and payment applications. Contains logging mechanisms for budget changes and error tracking.
A6: Metrics:
A7: - Total Sheets: | B7: 11 (excluding llm_README)
A8: - Visible Sheets: | B8: 11
A9: - Hidden Sheets: | B9: 0
A10: - Generation Mode: | B10: standard
A11: - Generated: | B11: 2025-08-03T04:47:55.965Z
A13: SHEET DETAILS
A15: Sheet: 00_JobSetup
A16: - Dimensions: | B16: 37 rows x 18 columns
A17: - Used Range: | B17: B2:D31
A18: - Headers: | B18: Row 7: Vendor (B7), Category (C7), Forecasted Cost Type (D7)
A20: Sheet: 01_ForecastLog
A21: - Dimensions: | B21: 66 rows x 6 columns
A22: - Used Range: | B22: B2:S38
A24: ═══════════════════════════════════════════
A25: DETAILED SHEET ANALYSIS
A26: ═══════════════════════════════════════════
A28: 1. 00_JobSetup (Type: Setup)
A29: Dimensions: | C29: 37 rows × 18 columns
A30: Used Range: | C30: A1:D31
A31: Purpose: | C31: Initial job configuration with property details and vendor assignments
A32: Headers Found: | C32: A7:, B7:Vendor, C7:Category, D7:Forecasted Cost Type
A34: 2. 01_ForecastLog (Type: Log)
A35: Dimensions: | C35: 66 rows × 6 columns
A36: Used Range: | C36: A1:S38
A37: Purpose: | C37: Tracks forecast changes and budget modifications over time
A38: Headers Found: | C38: A7:, B7:Category, C7:Budget Type, D7:Budget Amount, E7:Budget Status, F7:Date Entered, G7:Budget Notes, H7:, I7:, J7:, K7:, L7:, M7:, N7:, O7:, P7:, Q7:, R7:, S7:
A40: 3. 02_BudgetLog (Type: Log)
A41: Dimensions: | C41: 62 rows × 12 columns
A42: Used Range: | C42: A1:G67
A43: 4-10. Additional Sheets Summary: | C43: Detailed budget tracking log with categories and amounts
A44: • 03_BudgetReport: | C44: A7:, B7:Category, C7:Original Budget, D7:Approved Changes, E7:Revised Budget, F7:Revised Budget PSF, G7:Committed Cost | D44: Consolidated budget reporting with actuals vs forecasts
A45: • 04_VendorDetail: | D45: Vendor information and contract details
A46: • zz_data: | D46: Master data table with property and vendor information
A47: • ErrorLog: | D47: System error tracking and debugging log
A48: • zzz_yardi import: | D48: Yardi system data import staging area
A49: • TENANT_ESTIMATE: | D49: Tenant improvement cost estimates
A50: • PAY_APP: | D50: Payment application processing
A53: ═══════════════════════════════════════════
A54: GLOBAL ANALYSIS
A55: ═══════════════════════════════════════════
A57: • 00_JobSetup → references tblProperties table (in 04_VendorDetail sheet)
A58: • 00_JobSetup → references tblProperties table (likely in zz_data)
A59: • BudgetLog/ForecastLog → feed into BudgetReport
A60: • PAY_APP → processes vendor payments from VendorDetail
A61: • zzz_yardi import → external data source integration
A63: Identified Risks:
A64: • [MEDIUM] INDEX/MATCH formulas without error handling
A65: • [LOW] Multiple sheets with similar names (potential confusion)
A66: • [MEDIUM] No apparent data validation on input fields
... A95: • External integration via zzz_yardi import sheet

Sheet README_Instructions
B2: RJK CONSTRUCTION - BUDGET TRACKER
B3: Purpose:
B4: This workbook is the new required standard for all budgeting, estimating, job tracking, and forecasting of any kind for construction projects at RJ Kelly.
B6: Color Legend:
B7: Cells in blue font are for manual input by Project Managers. All other cells are locked.
B8: Cells in black font are formula's and are not able to be edited
B10: Workflow:
B11: Step 1: Job Setup: Navigate to '01_Job Setup' tab and fill in the project's high-level details and scope of work.
B12: Step 2: Build Forecast & Budget: Use Commitment, Estimate, and Budget Logs to create Forecast and Budget amounts that populate in '05_Budget_Report'. Based on Cost Code Category and Vendor. -'02_Commitment_Log' : Record Subcontracts, Subcontract Change Orders, and Material Purchase Orders. Feeds into PM Forecast when 'Approved' status. -'03_PCC_Log' : Record Probably Construction Cost (PCC) estimates. Feeds into PM Forecast when 'Approved' status. -'04_Budget_Log' : Record Original Budget and any Budget changes. Feeds into Original and Revised Budget.
B14: Step 3: Tracking and Updating Budget: Track & Forecast: As the job progresses: - Log all contracts and POs in the '03_Commitment_Log'. - Log all budget changes in the '04_Change_Order_Log'. - Regularly update the 'Invoiced Cost' and 'PM Forecasted Final Cost' columns on the '02_Budget_Forecast' sheet to maintain an accurate projection.
N20: PROJECT COST MANAGEMENT WORKBOOK - COMPREHENSIVE README
N21: Generated: 2025-07-20 00:29 UTC
N23: OVERVIEW
N24: This workbook is RJK Construction's standardized project cost management system for budget tracking, forecasting, and financial reporting of construction projects. It integrates job setup parameters, commitment logging, potential cost tracking, and budget management into a comprehensive dashboard that provides real-time budget vs. actual analysis with Power Pivot data model integration for historical invoice tracking.
N26: WORKBOOK STRUCTURE
N27: • Total Sheets: 11
N28: • Structured Tables: 8 (tblCommitments, tblPotentialCosts, tblBudetLog, tblBudget, tblProperties, tblVendors, tblCostCodes, tblLookups, ProjectManagers)
N29: • Power Pivot Data Model: Yes (ThisWorkbookDataModel with CUBE formulas)
N30: • VBA Macros: None
N31: • Charts: None currently
N33: SHEET-BY-SHEET GUIDE
N34: 1. README_Instructions
... N219: • Recommended naming: ProjectName_BudgetTracker_v1.0.xlsx

Sheet 00_JobSetup
B2: Job Setup
B3: Property: | C3: 40mallrd
B4: Job Name: | C4: 40 Mall Rd Ste 206 PreTI
B5: Job SF: | C5: 1328
B6: Project Manager: | C6: Craig Sorbello
B7: Job Status: | C7: IN PROGRESS
B8: Job Type: | C8: PRE TI
B9: Projected Start Date: | D9: Boots in ground? Permit submitted? When?
B10: Projected Completion Date: | D10: C of O?
B11: Yardi Job Code: | C11: dev-23
B12: Scope of Work:
B16: Fee/Contingency Setup
B17: CM Fee % : | D17: 007400 - Construction Management Fee
B18: GC Fee % : | D18: 007200 - GC Fee
B19: GC Insurance % : | D19: 007316 - GC Insurance
B20: Dev Fee Type : | D20: n/a
B21: Dev Fee $ : | D21: 001900 - Development Fee
B22: Dev Fee % : | D22: 001900 - Development Fee
B23: Soft Cost Contingency % : | D23: 001099 - Soft Costs - Other
B24: Owner Contingency % : | D24: 001980 - Owner Const Cost Contingency
B25: GC Contingency % : | D25: 012116 - GC Cost Contingency
B27: Billing Setup
B28: Client/Tenant: | C28: n/a
B29: Form Type: | C29: n/a | D29: Estimate, invoice, pay app
B30: Invoice Date:
B31: Invoice /AIA #:

Sheet 01_ForecastLog
B2: FORECAST LOG
B3: ='00_JobSetup'!$C$4 -> 40 Mall Rd Ste 206 PreTI
B4: =INDEX(tblProperties[#All],MATCH('00_JobSetup'!$C$3,tblProperties[[#All],[PropertyCode]],0),2) -> 40 Mall Road
B5: ='00_JobSetup'!C5 -> 1328 | G5: maybe remove?
B7: Vendor | C7: Category | D7: Forecasted Cost Type | E7: Forecasted Cost Amount | F7: Forecasted Cost Status | G7: Date Entered | H7: Commitment Notes
B8: 3 Phase Elevator Corp. | C8: 140010 - Elevator | D8: Initial Estimate | E8: 4000 | F8: Pending
B9: A & M Roofing & Sheet Metal Co., Inc
B10: Boucher Acoustic LLC | C10: 095000 - Ceilings | D10: Subcontract | E10: 6140 | F10: Accepted | G10: 45866 | M10: Vendor | N10: Category | O10: Forecasted Cost Type | P10: Forecasted Cost Amount | Q10: Forecasted Cost Status | R10: Date Entered | S10: Commitment Notes
B11: Commercial Fire Sprinkler, Inc. | C11: 210010 - Fire Suppression - Total | D11: Subcontract | E11: 3900 | F11: Accepted | G11: 45866
B12: GSD Associates, LLC | C12: 001010 - Architect Fee | D12: Purchase Order | E12: 4000
B13: Lapery Painting | C13: 099000 - Painting and Coating | D13: Subcontract | E13: 3940 | F13: Accepted | G13: 45866 | M13: Vendor
B14: Lapery Painting | C14: 099000 - Painting and Coating | D14: Subcontract CO #1 | E14: 1000 | F14: Accepted | M14: Category
B15: Paglia Plastering, Inc. | C15: 092000 - Framing and Drywall | D15: Subcontract | E15: 10100 | F15: Accepted | G15: 45866 | M15: Forecasted Cost Type
B16: Precision Demolition, Inc. | C16: 024000 - Demo - Total | D16: Subcontract | E16: 3100 | F16: Accepted | G16: 45866 | M16: Forecasted Cost Amount
B17: R&M Glass LLC | C17: 084300 - Storefronts | D17: Subcontract | E17: 1806 | F17: Accepted | G17: 45866 | M17: Forecasted Cost Status
B18: R&M Glass LLC | C18: 084300 - Storefronts | D18: Subcontract CO #1 | E18: 1806 | F18: Accepted | G18: 45866 | H18: added 6 windows | M18: Commitment Notes
B19: Rizzo's Floor Covering | C19: 096000 - Flooring | D19: Subcontract | E19: 500 | F19: Accepted | G19: 45866
B20: RJK Company, Inc. | C20: 008010 - Labor - Project Manager
B21: Systems Electrical Services Co., Inc. | C21: 260010 - Electrical - Total | D21: Subcontract | E21: 9325 | F21: Accepted | G21: 45866
B22: Able Air Corp
D38: FORECAST AMOUNT: | E38: =SUBTOTAL(109,tblForecastLog[Forecasted Cost Amount]) -> 49617

Sheet 04_VendorDetail
C2: Vendor Detail
C3: ='00_JobSetup'!C4 -> 40 Mall Rd Ste 206 PreTI
C4: =INDEX(tblProperties[#All],MATCH('00_JobSetup'!$C$3,tblProperties[[#All],[PropertyCode]],0),2) -> 40 Mall Road
C5: ='00_JobSetup'!C5 -> 1328
C7: Vendor Name | D7: Subcontract | E7: Change Orders | F7: Purchase Orders | G7: Total Committed | H7: Estimated Cost | I7: Invoiced to Date | J7: Project Manger Notes
A8: 3 Phase Elevator Corp. | B8: {=_xlfn.LET(_xlpm.idx,ROW()-ROW('04_VendorDetail'!$C$7),IFERROR(INDEX(Vendor_Name_index,_xlpm.idx),""))} | C8: {=_xlfn.LET(_xlpm.trig,RAND()*0,_xlpm.flList,_xlfn._xlws.FILTER(tblForecastLog[Vendor],tblForecastLog[Vendor]<>""),_xlpm.cubeSet,CUBESET("ThisWorkbookDataModel","[Fact_JobDetail].[_Vendor].Members"),_xlpm.setCnt,CUBESETCOUNT(_xlpm.cubeSet),_xlpm.dmRaw,_xlfn.MAP(_xlfn.SEQUENCE(_xlpm.setCnt),_xlfn.LAMBDA(_xlpm.i,IFERROR(CUBERANKEDMEMBER("ThisWorkbookDataModel",_xlpm.cubeSet,_xlpm.i),""))),_xlpm.dmList,_xlfn._xlws.FILTER(_xlpm.dmRaw,(_xlpm.dmRaw<>"")*(_xlpm.dmRaw<>"All")),_xlpm.combined,_xlfn.VSTACK(_xlpm.flList,_xlpm.dmList),_xlfn._xlws.SORT(_xlfn.UNIQUE(_xlpm.combined)))} -> #N/A | D8: =SUMIFS(tblForecastLog[Forecasted Cost Amount],tblForecastLog[Vendor],A8,tblForecastLog[Forecasted Cost Type],"Subcontract") -> 0 | E8: {=SUMPRODUCT((tblForecastLog[Vendor]=A8)*(ISNUMBER(SEARCH("CO",tblForecastLog[Forecasted Cost Type])))*(tblForecastLog[Forecasted Cost Amount]))+SUMIFS(tblForecastLog[Forecasted Cost Amount],tblForecastLog[Vendor],A8,tblForecastLog[Forecasted Cost Type],"Change Order")} -> 0 | F8: =SUMIFS(tblForecastLog[Forecasted Cost Amount],tblForecastLog[Vendor],A8,tblForecastLog[Forecasted Cost Type],"Purchase Order") -> 0 | G8: =SUM(D8:F8) -> 0 | H8: =SUMIF(tblForecastLog[Vendor],A8,tblForecastLog[Forecasted Cost Amount]) -> 4000 | I8: =_xlfn.IFNA(CUBEVALUE("ThisWorkbookDataModel","[Measures].[Amount by Vendor]",CUBEMEMBER("ThisWorkbookDataModel","[Fact_JobDetail].[_Vendor].&["&TRIM($C8)&"]")),0) -> 0
A9: A & M Roofing & Sheet Metal Co., Inc | D9: =SUMIFS(tblForecastLog[Forecasted Cost Amount],tblForecastLog[Vendor],A9,tblForecastLog[Forecasted Cost Type],"Subcontract") -> 0 | E9: {=SUMPRODUCT((tblForecastLog[Vendor]=A9)*(ISNUMBER(SEARCH("CO",tblForecastLog[Forecasted Cost Type])))*(tblForecastLog[Forecasted Cost Amount]))+SUMIFS(tblForecastLog[Forecasted Cost Amount],tblForecastLog[Vendor],A9,tblForecastLog[Forecasted Cost Type],"Change Order")} -> 0 | F9: =SUMIFS(tblForecastLog[Forecasted Cost Amount],tblForecastLog[Vendor],A9,tblForecastLog[Forecasted Cost Type],"Purchase Order") -> 0 | G9: =SUM(D9:F9) -> 0 | H9: =SUMIF(tblForecastLog[Vendor],A9,tblForecastLog[Forecasted Cost Amount]) -> 0 | I9: =_xlfn.IFNA(CUBEVALUE("ThisWorkbookDataModel","[Measures].[Amount by Vendor]",CUBEMEMBER("ThisWorkbookDataModel","[Fact_JobDetail].[_Vendor].&["&TRIM($C9)&"]")),0) -> 0
A10: Boucher Acoustic LLC | D10: =SUMIFS(tblForecastLog[Forecasted Cost Amount],tblForecastLog[Vendor],A10,tblForecastLog[Forecasted Cost Type],"Subcontract") -> 6140 | E10: {=SUMPRODUCT((tblForecastLog[Vendor]=A10)*(ISNUMBER(SEARCH("CO",tblForecastLog[Forecasted Cost Type])))*(tblForecastLog[Forecasted Cost Amount]))+SUMIFS(tblForecastLog[Forecasted Cost Amount],tblForecastLog[Vendor],A10,tblForecastLog[Forecasted Cost Type],"Change Order")} -> 6140 | F10: =SUMIFS(tblForecastLog[Forecasted Cost Amount],tblForecastLog[Vendor],A10,tblForecastLog[Forecasted Cost Type],"Purchase Order") -> 0 | G10: =SUM(D10:F10) -> 12280 | H10: =SUMIF(tblForecastLog[Vendor],A10,tblForecastLog[Forecasted Cost Amount]) -> 6140 | I10: =_xlfn.IFNA(CUBEVALUE("ThisWorkbookDataModel","[Measures].[Amount by Vendor]",CUBEMEMBER("ThisWorkbookDataModel","[Fact_JobDetail].[_Vendor].&["&TRIM($C10)&"]")),0) -> 0
A11: Commercial Fire Sprinkler, Inc. | D11: =SUMIFS(tblForecastLog[Forecasted Cost Amount],tblForecastLog[Vendor],A11,tblForecastLog[Forecasted Cost Type],"Subcontract") -> 3900 | E11: {=SUMPRODUCT((tblForecastLog[Vendor]=A11)*(ISNUMBER(SEARCH("CO",tblForecastLog[Forecasted Cost Type])))*(tblForecastLog[Forecasted Cost Amount]))+SUMIFS(tblForecastLog[Forecasted Cost Amount],tblForecastLog[Vendor],A11,tblForecastLog[Forecasted Cost Type],"Change Order")} -> 3900 | F11: =SUMIFS(tblForecastLog[Forecasted Cost Amount],tblForecastLog[Vendor],A11,tblForecastLog[Forecasted Cost Type],"Purchase Order") -> 0 | G11: =SUM(D11:F11) -> 7800 | H11: =SUMIF(tblForecastLog[Vendor],A11,tblForecastLog[Forecasted Cost Amount]) -> 3900 | I11: =_xlfn.IFNA(CUBEVALUE("ThisWorkbookDataModel","[Measures].[Amount by Vendor]",CUBEMEMBER("ThisWorkbookDataModel","[Fact_JobDetail].[_Vendor].&["&TRIM($C11)&"]")),0) -> 0
A12: GSD Associates, LLC | D12: =SUMIFS(tblForecastLog[Forecasted Cost Amount],tblForecastLog[Vendor],A12,tblForecastLog[Forecasted Cost Type],"Subcontract") -> 0 | E12: {=SUMPRODUCT((tblForecastLog[Vendor]=A12)*(ISNUMBER(SEARCH("CO",tblForecastLog[Forecasted Cost Type])))*(tblForecastLog[Forecasted Cost Amount]))+SUMIFS(tblForecastLog[Forecasted Cost Amount],tblForecastLog[Vendor],A12,tblForecastLog[Forecasted Cost Type],"Change Order")} -> 0 | F12: =SUMIFS(tblForecastLog[Forecasted Cost Amount],tblForecastLog[Vendor],A12,tblForecastLog[Forecasted Cost Type],"Purchase Order") -> 4000 | G12: =SUM(D12:F12) -> 4000 | H12: =SUMIF(tblForecastLog[Vendor],A12,tblForecastLog[Forecasted Cost Amount]) -> 4000 | I12: =_xlfn.IFNA(CUBEVALUE("ThisWorkbookDataModel","[Measures].[Amount by Vendor]",CUBEMEMBER("ThisWorkbookDataModel","[Fact_JobDetail].[_Vendor].&["&TRIM($C12)&"]")),0) -> 0
A13: Lapery Painting | D13: =SUMIFS(tblForecastLog[Forecasted Cost Amount],tblForecastLog[Vendor],A13,tblForecastLog[Forecasted Cost Type],"Subcontract") -> 3940 | E13: {=SUMPRODUCT((tblForecastLog[Vendor]=A13)*(ISNUMBER(SEARCH("CO",tblForecastLog[Forecasted Cost Type])))*(tblForecastLog[Forecasted Cost Amount]))+SUMIFS(tblForecastLog[Forecasted Cost Amount],tblForecastLog[Vendor],A13,tblForecastLog[Forecasted Cost Type],"Change Order")} -> 4940 | F13: =SUMIFS(tblForecastLog[Forecasted Cost Amount],tblForecastLog[Vendor],A13,tblForecastLog[Forecasted Cost Type],"Purchase Order") -> 0 | G13: =SUM(D13:F13) -> 8880 | H13: =SUMIF(tblForecastLog[Vendor],A13,tblForecastLog[Forecasted Cost Amount]) -> 4940 | I13: =_xlfn.IFNA(CUBEVALUE("ThisWorkbookDataModel","[Measures].[Amount by Vendor]",CUBEMEMBER("ThisWorkbookDataModel","[Fact_JobDetail].[_Vendor].&["&TRIM($C13)&"]")),0) -> 0
A14: Paglia Plastering, Inc. | D14: =SUMIFS(tblForecastLog[Forecasted Cost Amount],tblForecastLog[Vendor],A14,tblForecastLog[Forecasted Cost Type],"Subcontract") -> 10100 | E14: {=SUMPRODUCT((tblForecastLog[Vendor]=A14)*(ISNUMBER(SEARCH("CO",tblForecastLog[Forecasted Cost Type])))*(tblForecastLog[Forecasted Cost Amount]))+SUMIFS(tblForecastLog[Forecasted Cost Amount],tblForecastLog[Vendor],A14,tblForecastLog[Forecasted Cost Type],"Change Order")} -> 10100 | F14: =SUMIFS(tblForecastLog[Forecasted Cost Amount],tblForecastLog[Vendor],A14,tblForecastLog[Forecasted Cost Type],"Purchase Order") -> 0 | G14: =SUM(D14:F14) -> 20200 | H14: =SUMIF(tblForecastLog[Vendor],A14,tblForecastLog[Forecasted Cost Amount]) -> 10100 | I14: =_xlfn.IFNA(CUBEVALUE("ThisWorkbookDataModel","[Measures].[Amount by Vendor]",CUBEMEMBER("ThisWorkbookDataModel","[Fact_JobDetail].[_Vendor].&["&TRIM($C14)&"]")),0) -> 0
A15: Precision Demolition, Inc. | D15: =SUMIFS(tblForecastLog[Forecasted Cost Amount],tblForecastLog[Vendor],A15,tblForecastLog[Forecasted Cost Type],"Subcontract") -> 3100 | E15: {=SUMPRODUCT((tblForecastLog[Vendor]=A15)*(ISNUMBER(SEARCH("CO",tblForecastLog[Forecasted Cost Type])))*(tblForecastLog[Forecasted Cost Amount]))+SUMIFS(tblForecastLog[Forecasted Cost Amount],tblForecastLog[Vendor],A15,tblForecastLog[Forecasted Cost Type],"Change Order")} -> 3100 | F15: =SUMIFS(tblForecastLog[Forecasted Cost Amount],tblForecastLog[Vendor],A15,tblForecastLog[Forecasted Cost Type],"Purchase Order") -> 0 | G15: =SUM(D15:F15) -> 6200 | H15: =SUMIF(tblForecastLog[Vendor],A15,tblForecastLog[Forecasted Cost Amount]) -> 3100 | I15: =_xlfn.IFNA(CUBEVALUE("ThisWorkbookDataModel","[Measures].[Amount by Vendor]",CUBEMEMBER("ThisWorkbookDataModel","[Fact_JobDetail].[_Vendor].&["&TRIM($C15)&"]")),0) -> 0
A16: R&M Glass LLC | D16: =SUMIFS(tblForecastLog[Forecasted Cost Amount],tblForecastLog[Vendor],A16,tblForecastLog[Forecasted Cost Type],"Subcontract") -> 1806 | E16: {=SUMPRODUCT((tblForecastLog[Vendor]=A16)*(ISNUMBER(SEARCH("CO",tblForecastLog[Forecasted Cost Type])))*(tblForecastLog[Forecasted Cost Amount]))+SUMIFS(tblForecastLog[Forecasted Cost Amount],tblForecastLog[Vendor],A16,tblForecastLog[Forecasted Cost Type],"Change Order")} -> 3612 | F16: =SUMIFS(tblForecastLog[Forecasted Cost Amount],tblForecastLog[Vendor],A16,tblForecastLog[Forecasted Cost Type],"Purchase Order") -> 0 | G16: =SUM(D16:F16) -> 5418 | H16: =SUMIF(tblForecastLog[Vendor],A16,tblForecastLog[Forecasted Cost Amount]) -> 3612 | I16: =_xlfn.IFNA(CUBEVALUE("ThisWorkbookDataModel","[Measures].[Amount by Vendor]",CUBEMEMBER("ThisWorkbookDataModel","[Fact_JobDetail].[_Vendor].&["&TRIM($C16)&"]")),0) -> 0
A17: Rizzo's Floor Covering | D17: =SUMIFS(tblForecastLog[Forecasted Cost Amount],tblForecastLog[Vendor],A17,tblForecastLog[Forecasted Cost Type],"Subcontract") -> 500 | E17: {=SUMPRODUCT((tblForecastLog[Vendor]=A17)*(ISNUMBER(SEARCH("CO",tblForecastLog[Forecasted Cost Type])))*(tblForecastLog[Forecasted Cost Amount]))+SUMIFS(tblForecastLog[Forecasted Cost Amount],tblForecastLog[Vendor],A17,tblForecastLog[Forecasted Cost Type],"Change Order")} -> 500 | F17: =SUMIFS(tblForecastLog[Forecasted Cost Amount],tblForecastLog[Vendor],A17,tblForecastLog[Forecasted Cost Type],"Purchase Order") -> 0 | G17: =SUM(D17:F17) -> 1000 | H17: =SUMIF(tblForecastLog[Vendor],A17,tblForecastLog[Forecasted Cost Amount]) -> 500 | I17: =_xlfn.IFNA(CUBEVALUE("ThisWorkbookDataModel","[Measures].[Amount by Vendor]",CUBEMEMBER("ThisWorkbookDataModel","[Fact_JobDetail].[_Vendor].&["&TRIM($C17)&"]")),0) -> 0
A18: RJK Company, Inc. | D18: =SUMIFS(tblForecastLog[Forecasted Cost Amount],tblForecastLog[Vendor],A18,tblForecastLog[Forecasted Cost Type],"Subcontract") -> 0 | E18: {=SUMPRODUCT((tblForecastLog[Vendor]=A18)*(ISNUMBER(SEARCH("CO",tblForecastLog[Forecasted Cost Type])))*(tblForecastLog[Forecasted Cost Amount]))+SUMIFS(tblForecastLog[Forecasted Cost Amount],tblForecastLog[Vendor],A18,tblForecastLog[Forecasted Cost Type],"Change Order")} -> 0 | F18: =SUMIFS(tblForecastLog[Forecasted Cost Amount],tblForecastLog[Vendor],A18,tblForecastLog[Forecasted Cost Type],"Purchase Order") -> 0 | G18: =SUM(D18:F18) -> 0 | H18: =SUMIF(tblForecastLog[Vendor],A18,tblForecastLog[Forecasted Cost Amount]) -> 0 | I18: =_xlfn.IFNA(CUBEVALUE("ThisWorkbookDataModel","[Measures].[Amount by Vendor]",CUBEMEMBER("ThisWorkbookDataModel","[Fact_JobDetail].[_Vendor].&["&TRIM($C18)&"]")),0) -> 0
A19: Systems Electrical Services Co., Inc. | D19: =SUMIFS(tblForecastLog[Forecasted Cost Amount],tblForecastLog[Vendor],A19,tblForecastLog[Forecasted Cost Type],"Subcontract") -> 9325 | E19: {=SUMPRODUCT((tblForecastLog[Vendor]=A19)*(ISNUMBER(SEARCH("CO",tblForecastLog[Forecasted Cost Type])))*(tblForecastLog[Forecasted Cost Amount]))+SUMIFS(tblForecastLog[Forecasted Cost Amount],tblForecastLog[Vendor],A19,tblForecastLog[Forecasted Cost Type],"Change Order")} -> 9325 | F19: =SUMIFS(tblForecastLog[Forecasted Cost Amount],tblForecastLog[Vendor],A19,tblForecastLog[Forecasted Cost Type],"Purchase Order") -> 0 | G19: =SUM(D19:F19) -> 18650 | H19: =SUMIF(tblForecastLog[Vendor],A19,tblForecastLog[Forecasted Cost Amount]) -> 9325 | I19: =_xlfn.IFNA(CUBEVALUE("ThisWorkbookDataModel","[Measures].[Amount by Vendor]",CUBEMEMBER("ThisWorkbookDataModel","[Fact_JobDetail].[_Vendor].&["&TRIM($C19)&"]")),0) -> 0
A20: Able Air Corp | D20: =SUMIFS(tblForecastLog[Forecasted Cost Amount],tblForecastLog[Vendor],A20,tblForecastLog[Forecasted Cost Type],"Subcontract") -> 0 | E20: {=SUMPRODUCT((tblForecastLog[Vendor]=A20)*(ISNUMBER(SEARCH("CO",tblForecastLog[Forecasted Cost Type])))*(tblForecastLog[Forecasted Cost Amount]))+SUMIFS(tblForecastLog[Forecasted Cost Amount],tblForecastLog[Vendor],A20,tblForecastLog[Forecasted Cost Type],"Change Order")} -> 0 | F20: =SUMIFS(tblForecastLog[Forecasted Cost Amount],tblForecastLog[Vendor],A20,tblForecastLog[Forecasted Cost Type],"Purchase Order") -> 0 | G20: =SUM(D20:F20) -> 0 | H20: =SUMIF(tblForecastLog[Vendor],A20,tblForecastLog[Forecasted Cost Amount]) -> 0 | I20: =_xlfn.IFNA(CUBEVALUE("ThisWorkbookDataModel","[Measures].[Amount by Vendor]",CUBEMEMBER("ThisWorkbookDataModel","[Fact_JobDetail].[_Vendor].&["&TRIM($C20)&"]")),0) -> 0
A21: GSD Associates, LLC | D21: =SUMIFS(tblForecastLog[Forecasted Cost Amount],tblForecastLog[Vendor],A21,tblForecastLog[Forecasted Cost Type],"Subcontract") -> 0 | E21: {=SUMPRODUCT((tblForecastLog[Vendor]=A21)*(ISNUMBER(SEARCH("CO",tblForecastLog[Forecasted Cost Type])))*(tblForecastLog[Forecasted Cost Amount]))+SUMIFS(tblForecastLog[Forecasted Cost Amount],tblForecastLog[Vendor],A21,tblForecastLog[Forecasted Cost Type],"Change Order")} -> 0 | F21: =SUMIFS(tblForecastLog[Forecasted Cost Amount],tblForecastLog[Vendor],A21,tblForecastLog[Forecasted Cost Type],"Purchase Order") -> 4000 | G21: =SUM(D21:F21) -> 4000 | H21: =SUMIF(tblForecastLog[Vendor],A21,tblForecastLog[Forecasted Cost Amount]) -> 4000 | I21: =_xlfn.IFNA(CUBEVALUE("ThisWorkbookDataModel","[Measures].[Amount by Vendor]",CUBEMEMBER("ThisWorkbookDataModel","[Fact_JobDetail].[_Vendor].&["&TRIM($C21)&"]")),0) -> 0
I22: =_xlfn.IFNA(CUBEVALUE("ThisWorkbookDataModel","[Measures].[Amount by Vendor]",CUBEMEMBER("ThisWorkbookDataModel","[Fact_JobDetail].[_Vendor].&["&TRIM($C22)&"]")),0) -> 0 | L22: {=_xlfn.LET(_xlpm.cubeSet,CUBESET("ThisWorkbookDataModel","[Fact_JobDetail].[_Vendor].Members"),_xlfn.MAP(_xlfn.SEQUENCE(CUBESETCOUNT(_xlpm.cubeSet)),_xlfn.LAMBDA(_xlpm.i,CUBERANKEDMEMBER("ThisWorkbookDataModel",_xlpm.cubeSet,_xlpm.i))))} -> #N/A
I23: =_xlfn.IFNA(CUBEVALUE("ThisWorkbookDataModel","[Measures].[Amount by Vendor]",CUBEMEMBER("ThisWorkbookDataModel","[Fact_JobDetail].[_Vendor].&["&TRIM($C23)&"]")),0) -> 0
I24: =_xlfn.IFNA(CUBEVALUE("ThisWorkbookDataModel","[Measures].[Amount by Vendor]",CUBEMEMBER("ThisWorkbookDataModel","[Fact_JobDetail].[_Vendor].&["&TRIM($C24)&"]")),0) -> 0
I25: =_xlfn.IFNA(CUBEVALUE("ThisWorkbookDataModel","[Measures].[Amount by Vendor]",CUBEMEMBER("ThisWorkbookDataModel","[Fact_JobDetail].[_Vendor].&["&TRIM($C25)&"]")),0) -> 0
D92: =SUBTOTAL(109,'04_VendorDetail'!$D$8:$D$91) -> 38811 | F92: =SUBTOTAL(109,'04_VendorDetail'!$F$8:$F$91) -> 8000 | G92: =SUBTOTAL(109,'04_VendorDetail'!$G$8:$G$91) -> 88428 | H92: =SUBTOTAL(109,'04_VendorDetail'!$H$8:$H$91) -> 53617 | I92: =SUBTOTAL(109,'04_VendorDetail'!$I$8:$I$91) -> 0

Sheet 02_BudgetLog
B2: BUDGET LOG
B3: ='03_BudgetReport'!B3 -> 40 Mall Rd Ste 206 PreTI
B4: =INDEX(tblProperties[#All],MATCH('00_JobSetup'!$C$3,tblProperties[[#All],[PropertyCode]],0),2) -> 40 Mall Road
B5: ='00_JobSetup'!C5 -> 1328
B7: Category | C7: Budget Type | D7: Budget Amount | E7: Budget Status | F7: Date Entered | G7: Budget Notes
B8: 001100 - Building Permits and Fees | C8: Original Budget | D8: 686.63 | E8: Approved | F8: 45866 | G8: Initial PM Forecast
B9: 008010 - Labor - Project Manager | C9: Original Budget | D9: 3700 | E9: Approved | F9: 45866 | G9: Initial PM Forecast
B10: 008020 - Labor - Super | C10: Original Budget | D10: 2700 | E10: Approved | F10: 45866 | G10: Initial PM Forecast
B11: 008030 - Labor - Foreman | C11: Original Budget | D11: 1440 | E11: Approved | F11: 45866 | G11: Initial PM Forecast
B12: 008050 - Labor - General Labor | C12: Original Budget | D12: 960 | E12: Approved | F12: 45866 | G12: Initial PM Forecast
B13: 010010 - General Requirements - Total | C13: Original Budget | D13: 1558.56 | E13: Approved | F13: 45866 | G13: Initial PM Forecast
B14: 024000 - Demo - Total | C14: Original Budget | D14: 3100 | E14: Approved | F14: 45866 | G14: Initial PM Forecast
B15: 081000 - Doors, Frames, & Hardware | C15: Original Budget | D15: 4500 | E15: Approved | F15: 45866 | G15: Initial PM Forecast
B16: 084300 - Storefronts | C16: Original Budget | D16: 1806 | E16: Approved | F16: 45866 | G16: Initial PM Forecast
B17: 084400 - Blinds | C17: Original Budget | D17: 1050 | E17: Approved | F17: 45866 | G17: Initial PM Forecast
B18: 092000 - Framing and Drywall | C18: Original Budget | D18: 10100 | E18: Approved | F18: 45866 | G18: Initial PM Forecast
B19: 095000 - Ceilings | C19: Original Budget | D19: 6140 | E19: Approved | F19: 45866 | G19: Initial PM Forecast
... B24: 260010 - Electrical - Total | C24: Original Budget | D24: 9325 | E24: Approved | F24: 45866 | G24: Initial PM Forecast
B67: Total | D67: =SUBTOTAL(109,tblBudetLog[Budget Amount]) -> 57906.19

Sheet 03_BudgetReport
B2: BUDGET REPORT
B3: ='00_JobSetup'!C4 -> 40 Mall Rd Ste 206 PreTI
B4: =INDEX(tblProperties[#All],MATCH('00_JobSetup'!$C$3,tblProperties[[#All],[PropertyCode]],0),2) -> 40 Mall Road
B5: ='00_JobSetup'!C5 -> 1328
C6: (1) | D6: (2) | E6: (1)+(2)= (3) | G6: (a) | H6: (b) | I6: (a)+(b)= (c) | K6: (c) - (3)
B7: Category | C7: Original Budget | D7: Approved Changes | E7: Revised Budget | F7: Revised Budget PSF | G7: Committed Cost | H7: Estimated Costs | I7: Forecasted Final Cost | J7: Forecasted Cost PSF | K7: Forecasted (Over)/Under | L7: Invoiced to Date | M7: Project Manger Notes
B8: {=_xlfn.LET(_xlpm.trig,RAND()*0,_xlpm.wbRaw,_xlfn.VSTACK(tblForecastLog[Category],tblBudetLog[Category]),_xlpm.wbList,_xlfn._xlws.SORT(_xlfn.UNIQUE(_xlfn._xlws.FILTER(_xlpm.wbRaw,_xlpm.wbRaw<>""))),_xlpm.cubeSet,CUBESET("ThisWorkbookDataModel","[Fact_JobDetail].[_Category].Members"),_xlpm.setCnt,CUBESETCOUNT(_xlpm.cubeSet),_xlpm.dmList,_xlfn.MAP(_xlfn.SEQUENCE(_xlpm.setCnt),_xlfn.LAMBDA(_xlpm.i,CUBERANKEDMEMBER("ThisWorkbookDataModel",_xlpm.cubeSet,_xlpm.i))),_xlpm.fullList,_xlfn._xlws.SORT(_xlfn.UNIQUE(_xlfn._xlws.FILTER(_xlfn.VSTACK(_xlpm.wbList,_xlpm.dmList),_xlfn.VSTACK(_xlpm.wbList,_xlpm.dmList)<>"All"))),_xlpm.idx,ROW()-ROW(tblBudget[[#Headers],[Category]]),IFERROR(INDEX(_xlpm.fullList,_xlpm.idx),""))} | C8: =SUMIFS(tblBudetLog[Budget Amount],tblBudetLog[Category],tblBudget[[#This Row],[Category]],tblBudetLog[Budget Type],"Original Budget",tblBudetLog[Budget Status],"Approved") -> 0 | D8: =SUMIFS(tblBudetLog[Budget Amount],tblBudetLog[Category],tblBudget[[#This Row],[Category]],tblBudetLog[Budget Type],"Budget Adjustment") -> 0 | E8: =tblBudget[[#This Row],[Original Budget]]+tblBudget[[#This Row],[Approved Changes]] -> 0 | F8: =tblBudget[[#This Row],[Revised Budget]]/$B$5 -> 0 | G8: {=SUMPRODUCT((tblForecastLog[Category]=tblBudget[[#This Row],[Category]])*ISNUMBER(MATCH(tblForecastLog[Forecasted Cost Type],{"Actual Cost","Purchase Order","Subcontract","Subcontract CO #1","Subcontract CO #2","Subcontract CO #3","Subcontract CO #4","Subcontract CO #5","Subcontract CO #6","Subcontract CO #7","Subcontract CO #8","Subcontract CO #9","Subcontract CO #10"},0))*(tblForecastLog[Forecasted Cost Status]="Accepted")*tblForecastLog[Forecasted Cost Amount])} -> 0 | H8: {=SUMPRODUCT((tblForecastLog[Category]=tblBudget[[#This Row],[Category]])*ISNUMBER(MATCH(tblForecastLog[Forecasted Cost Type],{"Initial Estimate","Revised Estimate"},0))*ISNUMBER(MATCH(tblForecastLog[Forecasted Cost Status],{"Accepted","Pending"},0))*tblForecastLog[Forecasted Cost Amount])} -> 0 | I8: =tblBudget[[#This Row],[Committed Cost]]+tblBudget[[#This Row],[Estimated Costs]] -> 0 | J8: =tblBudget[[#This Row],[Forecasted Final Cost]]/$B$5 -> 0 | K8: =tblBudget[[#This Row],[Revised Budget]]-tblBudget[[#This Row],[Forecasted Final Cost]] -> 0 | L8: =_xlfn.IFNA(CUBEVALUE("ThisWorkbookDataModel","[Measures].[Amount by _Category]",CUBEMEMBER("ThisWorkbookDataModel","[Fact_JobDetail].[_Category].&["&TRIM($B8)&"]")),0) -> 0
B9: {=_xlfn.LET(_xlpm.trig,RAND()*0,_xlpm.wbRaw,_xlfn.VSTACK(tblForecastLog[Category],tblBudetLog[Category]),_xlpm.wbList,_xlfn._xlws.SORT(_xlfn.UNIQUE(_xlfn._xlws.FILTER(_xlpm.wbRaw,_xlpm.wbRaw<>""))),_xlpm.cubeSet,CUBESET("ThisWorkbookDataModel","[Fact_JobDetail].[_Category].Members"),_xlpm.setCnt,CUBESETCOUNT(_xlpm.cubeSet),_xlpm.dmList,_xlfn.MAP(_xlfn.SEQUENCE(_xlpm.setCnt),_xlfn.LAMBDA(_xlpm.i,CUBERANKEDMEMBER("ThisWorkbookDataModel",_xlpm.cubeSet,_xlpm.i))),_xlpm.fullList,_xlfn._xlws.SORT(_xlfn.UNIQUE(_xlfn._xlws.FILTER(_xlfn.VSTACK(_xlpm.wbList,_xlpm.dmList),_xlfn.VSTACK(_xlpm.wbList,_xlpm.dmList)<>"All"))),_xlpm.idx,ROW()-ROW(tblBudget[[#Headers],[Category]]),IFERROR(INDEX(_xlpm.fullList,_xlpm.idx),""))} | C9: =SUMIFS(tblBudetLog[Budget Amount],tblBudetLog[Category],tblBudget[[#This Row],[Category]],tblBudetLog[Budget Type],"Original Budget",tblBudetLog[Budget Status],"Approved") -> 0 | D9: =SUMIFS(tblBudetLog[Budget Amount],tblBudetLog[Category],tblBudget[[#This Row],[Category]],tblBudetLog[Budget Type],"Budget Adjustment") -> 0 | E9: =tblBudget[[#This Row],[Original Budget]]+tblBudget[[#This Row],[Approved Changes]] -> 0 | F9: =tblBudget[[#This Row],[Revised Budget]]/$B$5 -> 0 | G9: {=SUMPRODUCT((tblForecastLog[Category]=tblBudget[[#This Row],[Category]])*ISNUMBER(MATCH(tblForecastLog[Forecasted Cost Type],{"Actual Cost","Purchase Order","Subcontract","Subcontract CO #1","Subcontract CO #2","Subcontract CO #3","Subcontract CO #4","Subcontract CO #5","Subcontract CO #6","Subcontract CO #7","Subcontract CO #8","Subcontract CO #9","Subcontract CO #10"},0))*(tblForecastLog[Forecasted Cost Status]="Accepted")*tblForecastLog[Forecasted Cost Amount])} -> 0 | H9: {=SUMPRODUCT((tblForecastLog[Category]=tblBudget[[#This Row],[Category]])*ISNUMBER(MATCH(tblForecastLog[Forecasted Cost Type],{"Initial Estimate","Revised Estimate"},0))*ISNUMBER(MATCH(tblForecastLog[Forecasted Cost Status],{"Accepted","Pending"},0))*tblForecastLog[Forecasted Cost Amount])} -> 0 | I9: =tblBudget[[#This Row],[Committed Cost]]+tblBudget[[#This Row],[Estimated Costs]] -> 0 | J9: =tblBudget[[#This Row],[Forecasted Final Cost]]/$B$5 -> 0 | K9: =tblBudget[[#This Row],[Revised Budget]]-tblBudget[[#This Row],[Forecasted Final Cost]] -> 0 | L9: =_xlfn.IFNA(CUBEVALUE("ThisWorkbookDataModel","[Measures].[Amount by _Category]",CUBEMEMBER("ThisWorkbookDataModel","[Fact_JobDetail].[_Category].&["&TRIM($B9)&"]")),0) -> 0
B10: {=_xlfn.LET(_xlpm.trig,RAND()*0,_xlpm.wbRaw,_xlfn.VSTACK(tblForecastLog[Category],tblBudetLog[Category]),_xlpm.wbList,_xlfn._xlws.SORT(_xlfn.UNIQUE(_xlfn._xlws.FILTER(_xlpm.wbRaw,_xlpm.wbRaw<>""))),_xlpm.cubeSet,CUBESET("ThisWorkbookDataModel","[Fact_JobDetail].[_Category].Members"),_xlpm.setCnt,CUBESETCOUNT(_xlpm.cubeSet),_xlpm.dmList,_xlfn.MAP(_xlfn.SEQUENCE(_xlpm.setCnt),_xlfn.LAMBDA(_xlpm.i,CUBERANKEDMEMBER("ThisWorkbookDataModel",_xlpm.cubeSet,_xlpm.i))),_xlpm.fullList,_xlfn._xlws.SORT(_xlfn.UNIQUE(_xlfn._xlws.FILTER(_xlfn.VSTACK(_xlpm.wbList,_xlpm.dmList),_xlfn.VSTACK(_xlpm.wbList,_xlpm.dmList)<>"All"))),_xlpm.idx,ROW()-ROW(tblBudget[[#Headers],[Category]]),IFERROR(INDEX(_xlpm.fullList,_xlpm.idx),""))} | C10: =SUMIFS(tblBudetLog[Budget Amount],tblBudetLog[Category],tblBudget[[#This Row],[Category]],tblBudetLog[Budget Type],"Original Budget",tblBudetLog[Budget Status],"Approved") -> 0 | D10: =SUMIFS(tblBudetLog[Budget Amount],tblBudetLog[Category],tblBudget[[#This Row],[Category]],tblBudetLog[Budget Type],"Budget Adjustment") -> 0 | E10: =tblBudget[[#This Row],[Original Budget]]+tblBudget[[#This Row],[Approved Changes]] -> 0 | F10: =tblBudget[[#This Row],[Revised Budget]]/$B$5 -> 0 | G10: {=SUMPRODUCT((tblForecastLog[Category]=tblBudget[[#This Row],[Category]])*ISNUMBER(MATCH(tblForecastLog[Forecasted Cost Type],{"Actual Cost","Purchase Order","Subcontract","Subcontract CO #1","Subcontract CO #2","Subcontract CO #3","Subcontract CO #4","Subcontract CO #5","Subcontract CO #6","Subcontract CO #7","Subcontract CO #8","Subcontract CO #9","Subcontract CO #10"},0))*(tblForecastLog[Forecasted Cost Status]="Accepted")*tblForecastLog[Forecasted Cost Amount])} -> 0 | H10: {=SUMPRODUCT((tblForecastLog[Category]=tblBudget[[#This Row],[Category]])*ISNUMBER(MATCH(tblForecastLog[Forecasted Cost Type],{"Initial Estimate","Revised Estimate"},0))*ISNUMBER(MATCH(tblForecastLog[Forecasted Cost Status],{"Accepted","Pending"},0))*tblForecastLog[Forecasted Cost Amount])} -> 0 | I10: =tblBudget[[#This Row],[Committed Cost]]+tblBudget[[#This Row],[Estimated Costs]] -> 0 | J10: =tblBudget[[#This Row],[Forecasted Final Cost]]/$B$5 -> 0 | K10: =tblBudget[[#This Row],[Revised Budget]]-tblBudget[[#This Row],[Forecasted Final Cost]] -> 0 | L10: =_xlfn.IFNA(CUBEVALUE("ThisWorkbookDataModel","[Measures].[Amount by _Category]",CUBEMEMBER("ThisWorkbookDataModel","[Fact_JobDetail].[_Category].&["&TRIM($B10)&"]")),0) -> 0
B11: {=_xlfn.LET(_xlpm.trig,RAND()*0,_xlpm.wbRaw,_xlfn.VSTACK(tblForecastLog[Category],tblBudetLog[Category]),_xlpm.wbList,_xlfn._xlws.SORT(_xlfn.UNIQUE(_xlfn._xlws.FILTER(_xlpm.wbRaw,_xlpm.wbRaw<>""))),_xlpm.cubeSet,CUBESET("ThisWorkbookDataModel","[Fact_JobDetail].[_Category].Members"),_xlpm.setCnt,CUBESETCOUNT(_xlpm.cubeSet),_xlpm.dmList,_xlfn.MAP(_xlfn.SEQUENCE(_xlpm.setCnt),_xlfn.LAMBDA(_xlpm.i,CUBERANKEDMEMBER("ThisWorkbookDataModel",_xlpm.cubeSet,_xlpm.i))),_xlpm.fullList,_xlfn._xlws.SORT(_xlfn.UNIQUE(_xlfn._xlws.FILTER(_xlfn.VSTACK(_xlpm.wbList,_xlpm.dmList),_xlfn.VSTACK(_xlpm.wbList,_xlpm.dmList)<>"All"))),_xlpm.idx,ROW()-ROW(tblBudget[[#Headers],[Category]]),IFERROR(INDEX(_xlpm.fullList,_xlpm.idx),""))} | C11: =SUMIFS(tblBudetLog[Budget Amount],tblBudetLog[Category],tblBudget[[#This Row],[Category]],tblBudetLog[Budget Type],"Original Budget",tblBudetLog[Budget Status],"Approved") -> 0 | D11: =SUMIFS(tblBudetLog[Budget Amount],tblBudetLog[Category],tblBudget[[#This Row],[Category]],tblBudetLog[Budget Type],"Budget Adjustment") -> 0 | E11: =tblBudget[[#This Row],[Original Budget]]+tblBudget[[#This Row],[Approved Changes]] -> 0 | F11: =tblBudget[[#This Row],[Revised Budget]]/$B$5 -> 0 | G11: {=SUMPRODUCT((tblForecastLog[Category]=tblBudget[[#This Row],[Category]])*ISNUMBER(MATCH(tblForecastLog[Forecasted Cost Type],{"Actual Cost","Purchase Order","Subcontract","Subcontract CO #1","Subcontract CO #2","Subcontract CO #3","Subcontract CO #4","Subcontract CO #5","Subcontract CO #6","Subcontract CO #7","Subcontract CO #8","Subcontract CO #9","Subcontract CO #10"},0))*(tblForecastLog[Forecasted Cost Status]="Accepted")*tblForecastLog[Forecasted Cost Amount])} -> 0 | H11: {=SUMPRODUCT((tblForecastLog[Category]=tblBudget[[#This Row],[Category]])*ISNUMBER(MATCH(tblForecastLog[Forecasted Cost Type],{"Initial Estimate","Revised Estimate"},0))*ISNUMBER(MATCH(tblForecastLog[Forecasted Cost Status],{"Accepted","Pending"},0))*tblForecastLog[Forecasted Cost Amount])} -> 0 | I11: =tblBudget[[#This Row],[Committed Cost]]+tblBudget[[#This Row],[Estimated Costs]] -> 0 | J11: =tblBudget[[#This Row],[Forecasted Final Cost]]/$B$5 -> 0 | K11: =tblBudget[[#This Row],[Revised Budget]]-tblBudget[[#This Row],[Forecasted Final Cost]] -> 0 | L11: =_xlfn.IFNA(CUBEVALUE("ThisWorkbookDataModel","[Measures].[Amount by _Category]",CUBEMEMBER("ThisWorkbookDataModel","[Fact_JobDetail].[_Category].&["&TRIM($B11)&"]")),0) -> 0
B12: {=_xlfn.LET(_xlpm.trig,RAND()*0,_xlpm.wbRaw,_xlfn.VSTACK(tblForecastLog[Category],tblBudetLog[Category]),_xlpm.wbList,_xlfn._xlws.SORT(_xlfn.UNIQUE(_xlfn._xlws.FILTER(_xlpm.wbRaw,_xlpm.wbRaw<>""))),_xlpm.cubeSet,CUBESET("ThisWorkbookDataModel","[Fact_JobDetail].[_Category].Members"),_xlpm.setCnt,CUBESETCOUNT(_xlpm.cubeSet),_xlpm.dmList,_xlfn.MAP(_xlfn.SEQUENCE(_xlpm.setCnt),_xlfn.LAMBDA(_xlpm.i,CUBERANKEDMEMBER("ThisWorkbookDataModel",_xlpm.cubeSet,_xlpm.i))),_xlpm.fullList,_xlfn._xlws.SORT(_xlfn.UNIQUE(_xlfn._xlws.FILTER(_xlfn.VSTACK(_xlpm.wbList,_xlpm.dmList),_xlfn.VSTACK(_xlpm.wbList,_xlpm.dmList)<>"All"))),_xlpm.idx,ROW()-ROW(tblBudget[[#Headers],[Category]]),IFERROR(INDEX(_xlpm.fullList,_xlpm.idx),""))} | C12: =SUMIFS(tblBudetLog[Budget Amount],tblBudetLog[Category],tblBudget[[#This Row],[Category]],tblBudetLog[Budget Type],"Original Budget",tblBudetLog[Budget Status],"Approved") -> 0 | D12: =SUMIFS(tblBudetLog[Budget Amount],tblBudetLog[Category],tblBudget[[#This Row],[Category]],tblBudetLog[Budget Type],"Budget Adjustment") -> 0 | E12: =tblBudget[[#This Row],[Original Budget]]+tblBudget[[#This Row],[Approved Changes]] -> 0 | F12: =tblBudget[[#This Row],[Revised Budget]]/$B$5 -> 0 | G12: {=SUMPRODUCT((tblForecastLog[Category]=tblBudget[[#This Row],[Category]])*ISNUMBER(MATCH(tblForecastLog[Forecasted Cost Type],{"Actual Cost","Purchase Order","Subcontract","Subcontract CO #1","Subcontract CO #2","Subcontract CO #3","Subcontract CO #4","Subcontract CO #5","Subcontract CO #6","Subcontract CO #7","Subcontract CO #8","Subcontract CO #9","Subcontract CO #10"},0))*(tblForecastLog[Forecasted Cost Status]="Accepted")*tblForecastLog[Forecasted Cost Amount])} -> 0 | H12: {=SUMPRODUCT((tblForecastLog[Category]=tblBudget[[#This Row],[Category]])*ISNUMBER(MATCH(tblForecastLog[Forecasted Cost Type],{"Initial Estimate","Revised Estimate"},0))*ISNUMBER(MATCH(tblForecastLog[Forecasted Cost Status],{"Accepted","Pending"},0))*tblForecastLog[Forecasted Cost Amount])} -> 0 | I12: =tblBudget[[#This Row],[Committed Cost]]+tblBudget[[#This Row],[Estimated Costs]] -> 0 | J12: =tblBudget[[#This Row],[Forecasted Final Cost]]/$B$5 -> 0 | K12: =tblBudget[[#This Row],[Revised Budget]]-tblBudget[[#This Row],[Forecasted Final Cost]] -> 0 | L12: =_xlfn.IFNA(CUBEVALUE("ThisWorkbookDataModel","[Measures].[Amount by _Category]",CUBEMEMBER("ThisWorkbookDataModel","[Fact_JobDetail].[_Category].&["&TRIM($B12)&"]")),0) -> 0
B13: {=_xlfn.LET(_xlpm.trig,RAND()*0,_xlpm.wbRaw,_xlfn.VSTACK(tblForecastLog[Category],tblBudetLog[Category]),_xlpm.wbList,_xlfn._xlws.SORT(_xlfn.UNIQUE(_xlfn._xlws.FILTER(_xlpm.wbRaw,_xlpm.wbRaw<>""))),_xlpm.cubeSet,CUBESET("ThisWorkbookDataModel","[Fact_JobDetail].[_Category].Members"),_xlpm.setCnt,CUBESETCOUNT(_xlpm.cubeSet),_xlpm.dmList,_xlfn.MAP(_xlfn.SEQUENCE(_xlpm.setCnt),_xlfn.LAMBDA(_xlpm.i,CUBERANKEDMEMBER("ThisWorkbookDataModel",_xlpm.cubeSet,_xlpm.i))),_xlpm.fullList,_xlfn._xlws.SORT(_xlfn.UNIQUE(_xlfn._xlws.FILTER(_xlfn.VSTACK(_xlpm.wbList,_xlpm.dmList),_xlfn.VSTACK(_xlpm.wbList,_xlpm.dmList)<>"All"))),_xlpm.idx,ROW()-ROW(tblBudget[[#Headers],[Category]]),IFERROR(INDEX(_xlpm.fullList,_xlpm.idx),""))} | C13: =SUMIFS(tblBudetLog[Budget Amount],tblBudetLog[Category],tblBudget[[#This Row],[Category]],tblBudetLog[Budget Type],"Original Budget",tblBudetLog[Budget Status],"Approved") -> 0 | D13: =SUMIFS(tblBudetLog[Budget Amount],tblBudetLog[Category],tblBudget[[#This Row],[Category]],tblBudetLog[Budget Type],"Budget Adjustment") -> 0 | E13: =tblBudget[[#This Row],[Original Budget]]+tblBudget[[#This Row],[Approved Changes]] -> 0 | F13: =tblBudget[[#This Row],[Revised Budget]]/$B$5 -> 0 | G13: {=SUMPRODUCT((tblForecastLog[Category]=tblBudget[[#This Row],[Category]])*ISNUMBER(MATCH(tblForecastLog[Forecasted Cost Type],{"Actual Cost","Purchase Order","Subcontract","Subcontract CO #1","Subcontract CO #2","Subcontract CO #3","Subcontract CO #4","Subcontract CO #5","Subcontract CO #6","Subcontract CO #7","Subcontract CO #8","Subcontract CO #9","Subcontract CO #10"},0))*(tblForecastLog[Forecasted Cost Status]="Accepted")*tblForecastLog[Forecasted Cost Amount])} -> 0 | H13: {=SUMPRODUCT((tblForecastLog[Category]=tblBudget[[#This Row],[Category]])*ISNUMBER(MATCH(tblForecastLog[Forecasted Cost Type],{"Initial Estimate","Revised Estimate"},0))*ISNUMBER(MATCH(tblForecastLog[Forecasted Cost Status],{"Accepted","Pending"},0))*tblForecastLog[Forecasted Cost Amount])} -> 0 | I13: =tblBudget[[#This Row],[Committed Cost]]+tblBudget[[#This Row],[Estimated Costs]] -> 0 | J13: =tblBudget[[#This Row],[Forecasted Final Cost]]/$B$5 -> 0 | K13: =tblBudget[[#This Row],[Revised Budget]]-tblBudget[[#This Row],[Forecasted Final Cost]] -> 0 | L13: =_xlfn.IFNA(CUBEVALUE("ThisWorkbookDataModel","[Measures].[Amount by _Category]",CUBEMEMBER("ThisWorkbookDataModel","[Fact_JobDetail].[_Category].&["&TRIM($B13)&"]")),0) -> 0
B14: {=_xlfn.LET(_xlpm.trig,RAND()*0,_xlpm.wbRaw,_xlfn.VSTACK(tblForecastLog[Category],tblBudetLog[Category]),_xlpm.wbList,_xlfn._xlws.SORT(_xlfn.UNIQUE(_xlfn._xlws.FILTER(_xlpm.wbRaw,_xlpm.wbRaw<>""))),_xlpm.cubeSet,CUBESET("ThisWorkbookDataModel","[Fact_JobDetail].[_Category].Members"),_xlpm.setCnt,CUBESETCOUNT(_xlpm.cubeSet),_xlpm.dmList,_xlfn.MAP(_xlfn.SEQUENCE(_xlpm.setCnt),_xlfn.LAMBDA(_xlpm.i,CUBERANKEDMEMBER("ThisWorkbookDataModel",_xlpm.cubeSet,_xlpm.i))),_xlpm.fullList,_xlfn._xlws.SORT(_xlfn.UNIQUE(_xlfn._xlws.FILTER(_xlfn.VSTACK(_xlpm.wbList,_xlpm.dmList),_xlfn.VSTACK(_xlpm.wbList,_xlpm.dmList)<>"All"))),_xlpm.idx,ROW()-ROW(tblBudget[[#Headers],[Category]]),IFERROR(INDEX(_xlpm.fullList,_xlpm.idx),""))} | C14: =SUMIFS(tblBudetLog[Budget Amount],tblBudetLog[Category],tblBudget[[#This Row],[Category]],tblBudetLog[Budget Type],"Original Budget",tblBudetLog[Budget Status],"Approved") -> 0 | D14: =SUMIFS(tblBudetLog[Budget Amount],tblBudetLog[Category],tblBudget[[#This Row],[Category]],tblBudetLog[Budget Type],"Budget Adjustment") -> 0 | E14: =tblBudget[[#This Row],[Original Budget]]+tblBudget[[#This Row],[Approved Changes]] -> 0 | F14: =tblBudget[[#This Row],[Revised Budget]]/$B$5 -> 0 | G14: {=SUMPRODUCT((tblForecastLog[Category]=tblBudget[[#This Row],[Category]])*ISNUMBER(MATCH(tblForecastLog[Forecasted Cost Type],{"Actual Cost","Purchase Order","Subcontract","Subcontract CO #1","Subcontract CO #2","Subcontract CO #3","Subcontract CO #4","Subcontract CO #5","Subcontract CO #6","Subcontract CO #7","Subcontract CO #8","Subcontract CO #9","Subcontract CO #10"},0))*(tblForecastLog[Forecasted Cost Status]="Accepted")*tblForecastLog[Forecasted Cost Amount])} -> 0 | H14: {=SUMPRODUCT((tblForecastLog[Category]=tblBudget[[#This Row],[Category]])*ISNUMBER(MATCH(tblForecastLog[Forecasted Cost Type],{"Initial Estimate","Revised Estimate"},0))*ISNUMBER(MATCH(tblForecastLog[Forecasted Cost Status],{"Accepted","Pending"},0))*tblForecastLog[Forecasted Cost Amount])} -> 0 | I14: =tblBudget[[#This Row],[Committed Cost]]+tblBudget[[#This Row],[Estimated Costs]] -> 0 | J14: =tblBudget[[#This Row],[Forecasted Final Cost]]/$B$5 -> 0 | K14: =tblBudget[[#This Row],[Revised Budget]]-tblBudget[[#This Row],[Forecasted Final Cost]] -> 0 | L14: =_xlfn.IFNA(CUBEVALUE("ThisWorkbookDataModel","[Measures].[Amount by _Category]",CUBEMEMBER("ThisWorkbookDataModel","[Fact_JobDetail].[_Category].&["&TRIM($B14)&"]")),0) -> 0
B15: {=_xlfn.LET(_xlpm.trig,RAND()*0,_xlpm.wbRaw,_xlfn.VSTACK(tblForecastLog[Category],tblBudetLog[Category]),_xlpm.wbList,_xlfn._xlws.SORT(_xlfn.UNIQUE(_xlfn._xlws.FILTER(_xlpm.wbRaw,_xlpm.wbRaw<>""))),_xlpm.cubeSet,CUBESET("ThisWorkbookDataModel","[Fact_JobDetail].[_Category].Members"),_xlpm.setCnt,CUBESETCOUNT(_xlpm.cubeSet),_xlpm.dmList,_xlfn.MAP(_xlfn.SEQUENCE(_xlpm.setCnt),_xlfn.LAMBDA(_xlpm.i,CUBERANKEDMEMBER("ThisWorkbookDataModel",_xlpm.cubeSet,_xlpm.i))),_xlpm.fullList,_xlfn._xlws.SORT(_xlfn.UNIQUE(_xlfn._xlws.FILTER(_xlfn.VSTACK(_xlpm.wbList,_xlpm.dmList),_xlfn.VSTACK(_xlpm.wbList,_xlpm.dmList)<>"All"))),_xlpm.idx,ROW()-ROW(tblBudget[[#Headers],[Category]]),IFERROR(INDEX(_xlpm.fullList,_xlpm.idx),""))} | C15: =SUMIFS(tblBudetLog[Budget Amount],tblBudetLog[Category],tblBudget[[#This Row],[Category]],tblBudetLog[Budget Type],"Original Budget",tblBudetLog[Budget Status],"Approved") -> 0 | D15: =SUMIFS(tblBudetLog[Budget Amount],tblBudetLog[Category],tblBudget[[#This Row],[Category]],tblBudetLog[Budget Type],"Budget Adjustment") -> 0 | E15: =tblBudget[[#This Row],[Original Budget]]+tblBudget[[#This Row],[Approved Changes]] -> 0 | F15: =tblBudget[[#This Row],[Revised Budget]]/$B$5 -> 0 | G15: {=SUMPRODUCT((tblForecastLog[Category]=tblBudget[[#This Row],[Category]])*ISNUMBER(MATCH(tblForecastLog[Forecasted Cost Type],{"Actual Cost","Purchase Order","Subcontract","Subcontract CO #1","Subcontract CO #2","Subcontract CO #3","Subcontract CO #4","Subcontract CO #5","Subcontract CO #6","Subcontract CO #7","Subcontract CO #8","Subcontract CO #9","Subcontract CO #10"},0))*(tblForecastLog[Forecasted Cost Status]="Accepted")*tblForecastLog[Forecasted Cost Amount])} -> 0 | H15: {=SUMPRODUCT((tblForecastLog[Category]=tblBudget[[#This Row],[Category]])*ISNUMBER(MATCH(tblForecastLog[Forecasted Cost Type],{"Initial Estimate","Revised Estimate"},0))*ISNUMBER(MATCH(tblForecastLog[Forecasted Cost Status],{"Accepted","Pending"},0))*tblForecastLog[Forecasted Cost Amount])} -> 0 | I15: =tblBudget[[#This Row],[Committed Cost]]+tblBudget[[#This Row],[Estimated Costs]] -> 0 | J15: =tblBudget[[#This Row],[Forecasted Final Cost]]/$B$5 -> 0 | K15: =tblBudget[[#This Row],[Revised Budget]]-tblBudget[[#This Row],[Forecasted Final Cost]] -> 0 | L15: =_xlfn.IFNA(CUBEVALUE("ThisWorkbookDataModel","[Measures].[Amount by _Category]",CUBEMEMBER("ThisWorkbookDataModel","[Fact_JobDetail].[_Category].&["&TRIM($B15)&"]")),0) -> 0
B16: {=_xlfn.LET(_xlpm.trig,RAND()*0,_xlpm.wbRaw,_xlfn.VSTACK(tblForecastLog[Category],tblBudetLog[Category]),_xlpm.wbList,_xlfn._xlws.SORT(_xlfn.UNIQUE(_xlfn._xlws.FILTER(_xlpm.wbRaw,_xlpm.wbRaw<>""))),_xlpm.cubeSet,CUBESET("ThisWorkbookDataModel","[Fact_JobDetail].[_Category].Members"),_xlpm.setCnt,CUBESETCOUNT(_xlpm.cubeSet),_xlpm.dmList,_xlfn.MAP(_xlfn.SEQUENCE(_xlpm.setCnt),_xlfn.LAMBDA(_xlpm.i,CUBERANKEDMEMBER("ThisWorkbookDataModel",_xlpm.cubeSet,_xlpm.i))),_xlpm.fullList,_xlfn._xlws.SORT(_xlfn.UNIQUE(_xlfn._xlws.FILTER(_xlfn.VSTACK(_xlpm.wbList,_xlpm.dmList),_xlfn.VSTACK(_xlpm.wbList,_xlpm.dmList)<>"All"))),_xlpm.idx,ROW()-ROW(tblBudget[[#Headers],[Category]]),IFERROR(INDEX(_xlpm.fullList,_xlpm.idx),""))} | C16: =SUMIFS(tblBudetLog[Budget Amount],tblBudetLog[Category],tblBudget[[#This Row],[Category]],tblBudetLog[Budget Type],"Original Budget",tblBudetLog[Budget Status],"Approved") -> 0 | D16: =SUMIFS(tblBudetLog[Budget Amount],tblBudetLog[Category],tblBudget[[#This Row],[Category]],tblBudetLog[Budget Type],"Budget Adjustment") -> 0 | E16: =tblBudget[[#This Row],[Original Budget]]+tblBudget[[#This Row],[Approved Changes]] -> 0 | F16: =tblBudget[[#This Row],[Revised Budget]]/$B$5 -> 0 | G16: {=SUMPRODUCT((tblForecastLog[Category]=tblBudget[[#This Row],[Category]])*ISNUMBER(MATCH(tblForecastLog[Forecasted Cost Type],{"Actual Cost","Purchase Order","Subcontract","Subcontract CO #1","Subcontract CO #2","Subcontract CO #3","Subcontract CO #4","Subcontract CO #5","Subcontract CO #6","Subcontract CO #7","Subcontract CO #8","Subcontract CO #9","Subcontract CO #10"},0))*(tblForecastLog[Forecasted Cost Status]="Accepted")*tblForecastLog[Forecasted Cost Amount])} -> 0 | H16: {=SUMPRODUCT((tblForecastLog[Category]=tblBudget[[#This Row],[Category]])*ISNUMBER(MATCH(tblForecastLog[Forecasted Cost Type],{"Initial Estimate","Revised Estimate"},0))*ISNUMBER(MATCH(tblForecastLog[Forecasted Cost Status],{"Accepted","Pending"},0))*tblForecastLog[Forecasted Cost Amount])} -> 0 | I16: =tblBudget[[#This Row],[Committed Cost]]+tblBudget[[#This Row],[Estimated Costs]] -> 0 | J16: =tblBudget[[#This Row],[Forecasted Final Cost]]/$B$5 -> 0 | K16: =tblBudget[[#This Row],[Revised Budget]]-tblBudget[[#This Row],[Forecasted Final Cost]] -> 0 | L16: =_xlfn.IFNA(CUBEVALUE("ThisWorkbookDataModel","[Measures].[Amount by _Category]",CUBEMEMBER("ThisWorkbookDataModel","[Fact_JobDetail].[_Category].&["&TRIM($B16)&"]")),0) -> 0
B17: {=_xlfn.LET(_xlpm.trig,RAND()*0,_xlpm.wbRaw,_xlfn.VSTACK(tblForecastLog[Category],tblBudetLog[Category]),_xlpm.wbList,_xlfn._xlws.SORT(_xlfn.UNIQUE(_xlfn._xlws.FILTER(_xlpm.wbRaw,_xlpm.wbRaw<>""))),_xlpm.cubeSet,CUBESET("ThisWorkbookDataModel","[Fact_JobDetail].[_Category].Members"),_xlpm.setCnt,CUBESETCOUNT(_xlpm.cubeSet),_xlpm.dmList,_xlfn.MAP(_xlfn.SEQUENCE(_xlpm.setCnt),_xlfn.LAMBDA(_xlpm.i,CUBERANKEDMEMBER("ThisWorkbookDataModel",_xlpm.cubeSet,_xlpm.i))),_xlpm.fullList,_xlfn._xlws.SORT(_xlfn.UNIQUE(_xlfn._xlws.FILTER(_xlfn.VSTACK(_xlpm.wbList,_xlpm.dmList),_xlfn.VSTACK(_xlpm.wbList,_xlpm.dmList)<>"All"))),_xlpm.idx,ROW()-ROW(tblBudget[[#Headers],[Category]]),IFERROR(INDEX(_xlpm.fullList,_xlpm.idx),""))} | C17: =SUMIFS(tblBudetLog[Budget Amount],tblBudetLog[Category],tblBudget[[#This Row],[Category]],tblBudetLog[Budget Type],"Original Budget",tblBudetLog[Budget Status],"Approved") -> 0 | D17: =SUMIFS(tblBudetLog[Budget Amount],tblBudetLog[Category],tblBudget[[#This Row],[Category]],tblBudetLog[Budget Type],"Budget Adjustment") -> 0 | E17: =tblBudget[[#This Row],[Original Budget]]+tblBudget[[#This Row],[Approved Changes]] -> 0 | F17: =tblBudget[[#This Row],[Revised Budget]]/$B$5 -> 0 | G17: {=SUMPRODUCT((tblForecastLog[Category]=tblBudget[[#This Row],[Category]])*ISNUMBER(MATCH(tblForecastLog[Forecasted Cost Type],{"Actual Cost","Purchase Order","Subcontract","Subcontract CO #1","Subcontract CO #2","Subcontract CO #3","Subcontract CO #4","Subcontract CO #5","Subcontract CO #6","Subcontract CO #7","Subcontract CO #8","Subcontract CO #9","Subcontract CO #10"},0))*(tblForecastLog[Forecasted Cost Status]="Accepted")*tblForecastLog[Forecasted Cost Amount])} -> 0 | H17: {=SUMPRODUCT((tblForecastLog[Category]=tblBudget[[#This Row],[Category]])*ISNUMBER(MATCH(tblForecastLog[Forecasted Cost Type],{"Initial Estimate","Revised Estimate"},0))*ISNUMBER(MATCH(tblForecastLog[Forecasted Cost Status],{"Accepted","Pending"},0))*tblForecastLog[Forecasted Cost Amount])} -> 0 | I17: =tblBudget[[#This Row],[Committed Cost]]+tblBudget[[#This Row],[Estimated Costs]] -> 0 | J17: =tblBudget[[#This Row],[Forecasted Final Cost]]/$B$5 -> 0 | K17: =tblBudget[[#This Row],[Revised Budget]]-tblBudget[[#This Row],[Forecasted Final Cost]] -> 0 | L17: =_xlfn.IFNA(CUBEVALUE("ThisWorkbookDataModel","[Measures].[Amount by _Category]",CUBEMEMBER("ThisWorkbookDataModel","[Fact_JobDetail].[_Category].&["&TRIM($B17)&"]")),0) -> 0
B18: {=_xlfn.LET(_xlpm.trig,RAND()*0,_xlpm.wbRaw,_xlfn.VSTACK(tblForecastLog[Category],tblBudetLog[Category]),_xlpm.wbList,_xlfn._xlws.SORT(_xlfn.UNIQUE(_xlfn._xlws.FILTER(_xlpm.wbRaw,_xlpm.wbRaw<>""))),_xlpm.cubeSet,CUBESET("ThisWorkbookDataModel","[Fact_JobDetail].[_Category].Members"),_xlpm.setCnt,CUBESETCOUNT(_xlpm.cubeSet),_xlpm.dmList,_xlfn.MAP(_xlfn.SEQUENCE(_xlpm.setCnt),_xlfn.LAMBDA(_xlpm.i,CUBERANKEDMEMBER("ThisWorkbookDataModel",_xlpm.cubeSet,_xlpm.i))),_xlpm.fullList,_xlfn._xlws.SORT(_xlfn.UNIQUE(_xlfn._xlws.FILTER(_xlfn.VSTACK(_xlpm.wbList,_xlpm.dmList),_xlfn.VSTACK(_xlpm.wbList,_xlpm.dmList)<>"All"))),_xlpm.idx,ROW()-ROW(tblBudget[[#Headers],[Category]]),IFERROR(INDEX(_xlpm.fullList,_xlpm.idx),""))} | C18: =SUMIFS(tblBudetLog[Budget Amount],tblBudetLog[Category],tblBudget[[#This Row],[Category]],tblBudetLog[Budget Type],"Original Budget",tblBudetLog[Budget Status],"Approved") -> 0 | D18: =SUMIFS(tblBudetLog[Budget Amount],tblBudetLog[Category],tblBudget[[#This Row],[Category]],tblBudetLog[Budget Type],"Budget Adjustment") -> 0 | E18: =tblBudget[[#This Row],[Original Budget]]+tblBudget[[#This Row],[Approved Changes]] -> 0 | F18: =tblBudget[[#This Row],[Revised Budget]]/$B$5 -> 0 | G18: {=SUMPRODUCT((tblForecastLog[Category]=tblBudget[[#This Row],[Category]])*ISNUMBER(MATCH(tblForecastLog[Forecasted Cost Type],{"Actual Cost","Purchase Order","Subcontract","Subcontract CO #1","Subcontract CO #2","Subcontract CO #3","Subcontract CO #4","Subcontract CO #5","Subcontract CO #6","Subcontract CO #7","Subcontract CO #8","Subcontract CO #9","Subcontract CO #10"},0))*(tblForecastLog[Forecasted Cost Status]="Accepted")*tblForecastLog[Forecasted Cost Amount])} -> 0 | H18: {=SUMPRODUCT((tblForecastLog[Category]=tblBudget[[#This Row],[Category]])*ISNUMBER(MATCH(tblForecastLog[Forecasted Cost Type],{"Initial Estimate","Revised Estimate"},0))*ISNUMBER(MATCH(tblForecastLog[Forecasted Cost Status],{"Accepted","Pending"},0))*tblForecastLog[Forecasted Cost Amount])} -> 0 | I18: =tblBudget[[#This Row],[Committed Cost]]+tblBudget[[#This Row],[Estimated Costs]] -> 0 | J18: =tblBudget[[#This Row],[Forecasted Final Cost]]/$B$5 -> 0 | K18: =tblBudget[[#This Row],[Revised Budget]]-tblBudget[[#This Row],[Forecasted Final Cost]] -> 0 | L18: =_xlfn.IFNA(CUBEVALUE("ThisWorkbookDataModel","[Measures].[Amount by _Category]",CUBEMEMBER("ThisWorkbookDataModel","[Fact_JobDetail].[_Category].&["&TRIM($B18)&"]")),0) -> 0
B19: {=_xlfn.LET(_xlpm.trig,RAND()*0,_xlpm.wbRaw,_xlfn.VSTACK(tblForecastLog[Category],tblBudetLog[Category]),_xlpm.wbList,_xlfn._xlws.SORT(_xlfn.UNIQUE(_xlfn._xlws.FILTER(_xlpm.wbRaw,_xlpm.wbRaw<>""))),_xlpm.cubeSet,CUBESET("ThisWorkbookDataModel","[Fact_JobDetail].[_Category].Members"),_xlpm.setCnt,CUBESETCOUNT(_xlpm.cubeSet),_xlpm.dmList,_xlfn.MAP(_xlfn.SEQUENCE(_xlpm.setCnt),_xlfn.LAMBDA(_xlpm.i,CUBERANKEDMEMBER("ThisWorkbookDataModel",_xlpm.cubeSet,_xlpm.i))),_xlpm.fullList,_xlfn._xlws.SORT(_xlfn.UNIQUE(_xlfn._xlws.FILTER(_xlfn.VSTACK(_xlpm.wbList,_xlpm.dmList),_xlfn.VSTACK(_xlpm.wbList,_xlpm.dmList)<>"All"))),_xlpm.idx,ROW()-ROW(tblBudget[[#Headers],[Category]]),IFERROR(INDEX(_xlpm.fullList,_xlpm.idx),""))} | C19: =SUMIFS(tblBudetLog[Budget Amount],tblBudetLog[Category],tblBudget[[#This Row],[Category]],tblBudetLog[Budget Type],"Original Budget",tblBudetLog[Budget Status],"Approved") -> 0 | D19: =SUMIFS(tblBudetLog[Budget Amount],tblBudetLog[Category],tblBudget[[#This Row],[Category]],tblBudetLog[Budget Type],"Budget Adjustment") -> 0 | E19: =tblBudget[[#This Row],[Original Budget]]+tblBudget[[#This Row],[Approved Changes]] -> 0 | F19: =tblBudget[[#This Row],[Revised Budget]]/$B$5 -> 0 | G19: {=SUMPRODUCT((tblForecastLog[Category]=tblBudget[[#This Row],[Category]])*ISNUMBER(MATCH(tblForecastLog[Forecasted Cost Type],{"Actual Cost","Purchase Order","Subcontract","Subcontract CO #1","Subcontract CO #2","Subcontract CO #3","Subcontract CO #4","Subcontract CO #5","Subcontract CO #6","Subcontract CO #7","Subcontract CO #8","Subcontract CO #9","Subcontract CO #10"},0))*(tblForecastLog[Forecasted Cost Status]="Accepted")*tblForecastLog[Forecasted Cost Amount])} -> 0 | H19: {=SUMPRODUCT((tblForecastLog[Category]=tblBudget[[#This Row],[Category]])*ISNUMBER(MATCH(tblForecastLog[Forecasted Cost Type],{"Initial Estimate","Revised Estimate"},0))*ISNUMBER(MATCH(tblForecastLog[Forecasted Cost Status],{"Accepted","Pending"},0))*tblForecastLog[Forecasted Cost Amount])} -> 0 | I19: =tblBudget[[#This Row],[Committed Cost]]+tblBudget[[#This Row],[Estimated Costs]] -> 0 | J19: =tblBudget[[#This Row],[Forecasted Final Cost]]/$B$5 -> 0 | K19: =tblBudget[[#This Row],[Revised Budget]]-tblBudget[[#This Row],[Forecasted Final Cost]] -> 0 | L19: =_xlfn.IFNA(CUBEVALUE("ThisWorkbookDataModel","[Measures].[Amount by _Category]",CUBEMEMBER("ThisWorkbookDataModel","[Fact_JobDetail].[_Category].&["&TRIM($B19)&"]")),0) -> 0
... B63: {=_xlfn.LET(_xlpm.trig,RAND()*0,_xlpm.wbRaw,_xlfn.VSTACK(tblForecastLog[Category],tblBudetLog[Category]),_xlpm.wbList,_xlfn._xlws.SORT(_xlfn.UNIQUE(_xlfn._xlws.FILTER(_xlpm.wbRaw,_xlpm.wbRaw<>""))),_xlpm.cubeSet,CUBESET("ThisWorkbookDataModel","[Fact_JobDetail].[_Category].Members"),_xlpm.setCnt,CUBESETCOUNT(_xlpm.cubeSet),_xlpm.dmList,_xlfn.MAP(_xlfn.SEQUENCE(_xlpm.setCnt),_xlfn.LAMBDA(_xlpm.i,CUBERANKEDMEMBER("ThisWorkbookDataModel",_xlpm.cubeSet,_xlpm.i))),_xlpm.fullList,_xlfn._xlws.SORT(_xlfn.UNIQUE(_xlfn._xlws.FILTER(_xlfn.VSTACK(_xlpm.wbList,_xlpm.dmList),_xlfn.VSTACK(_xlpm.wbList,_xlpm.dmList)<>"All"))),_xlpm.idx,ROW()-ROW(tblBudget[[#Headers],[Category]]),IFERROR(INDEX(_xlpm.fullList,_xlpm.idx),""))} | C63: =SUMIFS(tblBudetLog[Budget Amount],tblBudetLog[Category],tblBudget[[#This Row],[Category]],tblBudetLog[Budget Type],"Original Budget",tblBudetLog[Budget Status],"Approved") -> 0 | D63: =SUMIFS(tblBudetLog[Budget Amount],tblBudetLog[Category],tblBudget[[#This Row],[Category]],tblBudetLog[Budget Type],"Budget Adjustment") -> 0 | E63: =tblBudget[[#This Row],[Original Budget]]+tblBudget[[#This Row],[Approved Changes]] -> 0 | F63: =tblBudget[[#This Row],[Revised Budget]]/$B$5 -> 0 | G63: {=SUMPRODUCT((tblForecastLog[Category]=tblBudget[[#This Row],[Category]])*ISNUMBER(MATCH(tblForecastLog[Forecasted Cost Type],{"Actual Cost","Purchase Order","Subcontract","Subcontract CO #1","Subcontract CO #2","Subcontract CO #3","Subcontract CO #4","Subcontract CO #5","Subcontract CO #6","Subcontract CO #7","Subcontract CO #8","Subcontract CO #9","Subcontract CO #10"},0))*(tblForecastLog[Forecasted Cost Status]="Accepted")*tblForecastLog[Forecasted Cost Amount])} -> 0 | H63: {=SUMPRODUCT((tblForecastLog[Category]=tblBudget[[#This Row],[Category]])*ISNUMBER(MATCH(tblForecastLog[Forecasted Cost Type],{"Initial Estimate","Revised Estimate"},0))*ISNUMBER(MATCH(tblForecastLog[Forecasted Cost Status],{"Accepted","Pending"},0))*tblForecastLog[Forecasted Cost Amount])} -> 0 | I63: =tblBudget[[#This Row],[Committed Cost]]+tblBudget[[#This Row],[Estimated Costs]] -> 0 | J63: =tblBudget[[#This Row],[Forecasted Final Cost]]/$B$5 -> 0 | K63: =tblBudget[[#This Row],[Revised Budget]]-tblBudget[[#This Row],[Forecasted Final Cost]] -> 0 | L63: =_xlfn.IFNA(CUBEVALUE("ThisWorkbookDataModel","[Measures].[Amount by _Category]",CUBEMEMBER("ThisWorkbookDataModel","[Fact_JobDetail].[_Category].&["&TRIM($B63)&"]")),0) -> 0
C64: =SUBTOTAL(109,tblBudget[Original Budget]) -> 0 | D64: =SUBTOTAL(109,tblBudget[Approved Changes]) -> 0 | E64: =SUBTOTAL(109,tblBudget[Revised Budget]) -> 0 | F64: =SUBTOTAL(109,tblBudget[Revised Budget PSF]) -> 0 | G64: =SUBTOTAL(109,tblBudget[Committed Cost]) -> 0 | H64: =SUBTOTAL(109,tblBudget[Estimated Costs]) -> 0 | I64: =SUBTOTAL(109,tblBudget[Forecasted Final Cost]) -> 0 | J64: =SUBTOTAL(109,tblBudget[Forecasted Cost PSF]) -> 0 | K64: =SUBTOTAL(109,tblBudget[Forecasted (Over)/Under]) -> 0 | L64: =SUBTOTAL(109,tblBudget[Invoiced to Date]) -> 0

Sheet zz_data
B1: PropertyCode | C1: PropertyName | E1: ProjectManager | G1: VendorCode | H1: VendorName | J1: Category | K1: CostCode | L1: Description | N1: JobType | O1: JobStatus | P1: DevFeeType | Q1: ForecastType | R1: ForecastStatus | S1: BudgetType | T1: BudgetStatus | V1: Vendors_Dynamic
B2: 100_q | C2: 100 Quannapowitt Parkway | E2: Doug Malone | G2: 3.phase | H2: 3 Phase Elevator Corp. | J2: 001010 - Architect Fee | K2: 001010 | L2: Architect Fee | N2: TI | O2: BUDGETING | P2: n/a | Q2: Initial Estimate | R2: Pending | S2: Original Budget | T2: Pending | V2: {=_xlfn.LET(_xlpm.dmSet,CUBESET("ThisWorkbookDataModel","[Fact_JobDetail].[_Vendor].Members"),_xlpm.dmCnt,CUBESETCOUNT(_xlpm.dmSet),_xlpm.dmList,_xlfn.MAP(_xlfn.SEQUENCE(_xlpm.dmCnt),_xlfn.LAMBDA(_xlpm.i,IFERROR(CUBERANKEDMEMBER("ThisWorkbookDataModel",_xlpm.dmSet,_xlpm.i),""))),_xlpm.wbRaw,_xlfn.VSTACK(tblForecastLog[Vendor],_xlpm.dmList),_xlfn._xlws.SORT(_xlfn.UNIQUE(_xlfn._xlws.FILTER(_xlpm.wbRaw,_xlpm.wbRaw<>""))))} -> #N/A
B3: 10columb | C3: 10 Columbia Drive | E3: Craig Sorbello | G3: amconst | H3: A & M Const Co Inc | J3: 001015 - Landscape Architect | K3: 001015 | L3: Landscape Architect | N3: PRE TI | O3: SCHEDULED | P3: Fixed | Q3: Revised Estimate | R3: Accepted | S3: Budget Adjustment | T3: Approved
B4: 10state | C4: 10 State Street | E4: Michael Camire | G4: amroofing | H4: A & M Roofing & Sheet Metal Co., Inc | J4: 001030 - MEP Engineering Fee | K4: 001030 | L4: MEP Engineering Fee | N4: CAPEX | O4: IN PROGRESS | P4: Percentage | Q4: Actual Cost | R4: Cancelled | S4: Change Order | T4: Rejected
B5: 111sbed | C5: 111 South Bedford | E5: Brendan Leahy | G5: rose | H5: A J Rose Carpet & Rugs | J5: 001040 - Civil Engineering Fee | K5: 001040 | L5: Civil Engineering Fee | N5: DEV | O5: COMPLETED | Q5: Purchase Order
B6: 11delta | C6: 11 Delta Drive | E6: Andy Frey | G6: abcsupp | H6: ABC Supply Co., Inc. - MBA #737 | J6: 001045 - Other Consultant Fees | K6: 001045 | L6: Other Consultant Fees | N6: GC | O6: CLOSED | Q6: Subcontract
B7: 11exec | C7: 11 Executive Park | G7: ableair | H7: Able Air Corp | J7: 001050 - Environmental Engineering Fee | K7: 001050 | L7: Environmental Engineering Fee | O7: CANCELLED | Q7: Subcontract CO #1
B8: 12_exec | C8: 12 Executive Drive | G8: aic | H8: Acadia Insurance Company | J8: 001060 - Traffic Engineering Fee | K8: 001060 | L8: Traffic Engineering Fee | Q8: Subcontract CO #2
B9: 121tech | C9: 121 Technology Drive | G9: accurateair | H9: Accurate Air | J9: 001070 - Geotech Engineering Fee | K9: 001070 | L9: Geotech Engineering Fee | Q9: Subcontract CO #3
B10: 12inno | C10: 12 Innovation | G10: acmgroup | H10: ACM Group, Inc. | J10: 001080 - Structural Engineering Fee | K10: 001080 | L10: Structural Engineering Fee | Q10: Subcontract CO #4
B11: 12kent | C11: 12 Kent Way | G11: agj | H11: AGJ Construction Inc. | J11: 001090 - Legal | K11: 001090 | L11: Legal | Q11: Subcontract CO #5
B12: 13hampsh | C12: 13 Hampshire Drive | G12: airdesign | H12: Air Design Services, Inc. | J12: 001099 - Soft Costs - Other | K12: 001099 | L12: Soft Costs - Other | Q12: Subcontract CO #6
B13: 14celina | C13: 14 Celina Avenue | G13: amai | H13: Allen & Major Associates, Inc. | J13: 001100 - Building Permits and Fees | K13: 001100 | L13: Building Permits and Fees | Q13: Subcontract CO #7
B14: 153range | C14: 153 Rangeway Road | G14: alscustom | H14: Al's Custom Tile | J14: 001900 - Development Fee | K14: 001900 | L14: Development Fee | Q14: Subcontract CO #8
B15: 15cont | C15: 15 Continental Boulevard | G15: baysideengin | H15: Bayside Engineering, Inc. | J15: 001910 - Mgmt & Supervision | K15: 001910 | L15: Mgmt & Supervision | Q15: Subcontract CO #9
B16: 15guest | C16: 15 Guest Street | G16: boodryelect | H16: Boodry Electric LLC | J16: 001980 - Owner Const Cost Contingency | K16: 001980 | L16: Owner Const Cost Contingency | Q16: Subcontract CO #10
B17: 16celina | C17: 16 Celina Avenue | G17: bbw | H17: Boston Building Wraps, INC | J17: 001998 - Builders Risk | K17: 001998 | L17: Builders Risk
B18: 16delta | C18: 16 Delta Drive | G18: boucher | H18: Boucher Acoustic LLC | J18: 007200 - GC Fee | K18: 007200 | L18: GC Fee
B19: 17_22del | C19: 17 & 22 Delta | G19: burlingtonlu | H19: Burlington Lumber Co. | J19: 007316 - GC Insurance | K19: 007316 | L19: GC Insurance
B20: 17hampsh | C20: 17 Hampshire Avenue | G20: campbell | H20: Campbell Co Electric LLC | J20: 007400 - Construction Management Fee | K20: 007400 | L20: Construction Management Fee
B21: 18celina | C21: 18 Celina Ave | G21: carlyle | H21: Carlyle Investment Management LLC | J21: 008010 - Labor - Project Manager | K21: 008010 | L21: Labor - Project Manager
B22: 18cont | C22: 18 Continental Boulevard | G22: casella | H22: Casella Waste Systems, Inc. | J22: 008020 - Labor - Super | K22: 008020 | L22: Labor - Super
B23: 20blanch | C23: 20 Blanchard Road | G23: bostonfire | H23: City of Boston | J23: 008030 - Labor - Foreman | K23: 008030 | L23: Labor - Foreman
B24: 20cont | C24: 20 Continental Boulevard | G24: methuen.plan | H24: City of Methuen | J24: 008040 - Labor - Carpenter | K24: 008040 | L24: Labor - Carpenter
B25: 24flagst | C25: 24 Flagstone Drive | G25: codered | H25: Code Red Consultants, LLC | J25: 008050 - Labor - General Labor | K25: 008050 | L25: Labor - General Labor
B26: 290shrew | C26: 290 Shrewsbury Street | G26: cohasset | H26: Cohasset Investment and Development LLC | J26: 010010 - General Requirements - Total | K26: 010010 | L26: General Requirements - Total
B27: 326_bal | C27: 326 Ballardvale LLC | G27: cds | H27: Commercial Drapery Systems | J27: 012116 - GC Cost Contingency | K27: 012116 | L27: GC Cost Contingency
B28: 33cherry | C28: 33 Cherry Hill Drive | G28: cfsi-jason | H28: Commercial Fire Sprinkler, Inc. | J28: 012119 - Testing and Inspection Allow | K28: 012119 | L28: Testing and Inspection Allow
... B63: 101stat | C63: 101 Station Landing | G63: kam | H63: Kamco Supply Corp. of Boston | J63: 096000 - Flooring | K63: 096000 | L63: Flooring
G64: kannanpricon | H64: Kannan & Pricone Plumbing & Heating Inc | J64: 096119 - Concrete Floor Staining | K64: 096119 | L64: Concrete Floor Staining
G65: kjm | H65: KJ Miller Mechanical | J65: 096800 - Carpeting | K65: 096800 | L65: Carpeting
G66: lapery | H66: Lapery Painting | J66: 099000 - Painting and Coating | K66: 099000 | L66: Painting and Coating
G67: lk | H67: Locks & Keys, Inc | J67: 100010 - Specialties - Total | K67: 100010 | L67: Specialties - Total
G68: lumens | H68: Lumens | J68: 100151 - Parking Lot | K68: 100151 | L68: Parking Lot
G69: mci | H69: Mass Cabinets Inc. | J69: 100191 - Building Exterior - Facade | K69: 100191 | L69: Building Exterior - Facade
G70: mcservices | H70: MC Services, LLC | J70: 105000 - Storage Specialties | K70: 105000 | L70: Storage Specialties
G71: mccarthyson | H71: McCarthy & Son Landscaping, Inc | J71: 100561 - Millwork | K71: 100561 | L71: Millwork
G72: mcp | H72: McSweeney Painting Co. | J72: 101400 - Signage | K72: 101400 | L72: Signage
G73: mdw | H73: MD Weaver Corporation | J73: 102200 - Partitions | K73: 102200 | L73: Partitions
G74: metal | H74: Metalcraft Door Co., Inc. | J74: 107313 - Awnings | K74: 107313 | L74: Awnings
G75: camire.micha | H75: Michael Camire | J75: 110010 - Equipment - Total | K75: 110010 | L75: Equipment - Total
... G95: scotland | H95: Scotland Bridge Woodworking | J95: 329000 - Landscaping | K95: 329000 | L95: Landscaping
G96: servmaster | H96: ServiceMaster Restore
G97: sgt | H97: Sonnys Glass Tinting LLC
G98: spark | H98: Spark Electrician Services LLC
G99: sec | H99: Stanley Elevator Co., Inc.
G100: steelblue | H100: Steelblue Building Components LLC
G101: stellos | H101: Stellos Electric Supply Inc.
G102: stalarm | H102: Steven D. Tanner
G103: ssi | H103: Structural Systems, Inc.
G104: sr | H104: Sunbelt Rentals
G105: sesci | H105: Systems Electrical Services Co., Inc.
G106: gran.place | H106: The Granite Place
G107: mcg | H107: The Morin-Cameron Group, Inc.
... G124: n/a | H124: n/a - estimate only

Sheet ErrorLog
A1: Timestamp | B1: Error # | C1: Description | D1: Procedure | E1: Object Context | F1: Line #
A2: 45830.898 | B2: 91 | C2: Object variable or With block variable not set | D2: LogError | E2: Data validation on 'tblCommitments' | F2: 8140
A3: 45830.898 | B3: 91 | C3: Object variable or With block variable not set | D3: LogError | E3: Data validation on 'tblChangeOrders' | F3: 9140
A4: 45830.898 | B4: 91 | C4: Object variable or With block variable not set | D4: LogError | E4: Setting formulas in 'tblBudget' | F4: 7160

Sheet zzz_yardi import
A1: Grey shaded cells should not be edited to successfully import
A3: Job Detail Id | B3: Category | C3: Description | D3: Budget | E3: Revision | F3: Remarks
A4: 4124 | B4: 001010 | C4: Architect Fee | D4: 0 | E4: 0
A5: 4209 | B5: 001030 | C5: MEP Engineering Fee | D5: 0 | E5: 0
A6: 4171 | B6: 001100 | C6: Building Permits and Fees | D6: 0 | E6: 0
A7: 4386 | B7: 007200 | C7: GC Fee | D7: 0 | E7: 0
A8: 4387 | B8: 007316 | C8: GC Insurance | D8: 0 | E8: 0
A9: 4385 | B9: 007400 | C9: Construction Management Fee | D9: 0 | E9: 0
A10: 4105 | B10: 008010 | C10: Labor - Project Manager | D10: 0 | E10: 0
A11: 4939 | B11: 008020 | C11: Labor - Super | D11: 0 | E11: 0
A12: 4360 | B12: 008040 | C12: Labor - Carpenter | D12: 0 | E12: 0
A13: 4656 | B13: 008050 | C13: Labor - General Labor | D13: 0 | E13: 0
A14: 4420 | B14: 010010 | C14: General Requirements - Total | D14: 0 | E14: 0
A15: 4587 | B15: 014126 | C15: Permit Requirements | D15: 0 | E15: 0
... A27: 4916 | B27: 310010 | C27: Sitework - Total | D27: 0 | E27: 0

Sheet TENANT_ESTIMATE
C1: ESTIMATE
C2: Date | D2: Estimate Prepared By
A3: 55 Cambridge Street - Suite 300
A4: Burlington, MA 01803
A5: (781)-272-2899
A7: Project: | B7: Lobby-Bldg Upgrade
A8: Location: | B8: 60 Mall Rd
A9: Client:
A10: Client Contact:
A12: Description of Work:
A17: Total Cost | D17: 935092.12
A19: * Price includes any Taxes, Materials, Labor, and Fees. * Payment is due 50% upon Estimate execution, and the balance upon completion of the Estimated Work. * All work to be performed during normal business hours unless otherwise noted. * Pricing is good for 30 days.
A20: All material is guaranteed to be as specified. All work to be completed and supervised by the R.J. Kelly Co., Inc. in accordance with specifications submitted in this estimate. Any alteration or deviation from above specifications involving additional extra costs will be executed only upon additional written change orders and will become an additional extra on the project. Tenant will be responsible for the costs associated with any changes to original project. In the event of any material or intent discretion between the Lease Agreement and any subsequently produced construction documents the Lease Agreement shall apply unless specifically outlined and noted as a "specific scope change" within an accepted change order between RJK Co and Tenant or authorized representative.
A22: Estimate Acceptance By:
A24: ______________________________________________________________ | D24: ____________________
A25: Tenant Representative | D25: Date

Sheet PAY_APP
E1: RJ Kelly Co., Inc. | G1: For: | H1: 121 Tech Owner LLC | K1: App. No. | L1: 5 | S1: RJ Kelly Co., Inc. | U1: For: | V1: =H1 -> 121 Tech Owner LLC | Y1: App. No. | Z1: =L1 -> 5
E2: 55 Cambridge Street | H2: 55 Cambridge Street | K2: Date: | L2: =TODAY() -> 45872 | S2: 55 Cambridge Street | V2: =H2 -> 55 Cambridge Street | Y2: Date: | Z2: =L2 -> 45872
E3: Burlington, MA 01803 | H3: Burlington, MA 01803 | K3: Period Start: | L3: 45231 | S3: Burlington, MA 01803 | V3: =H3 -> Burlington, MA 01803 | Y3: Period Start: | Z3: =L3 -> 45231
E4: p: (781) 272-2899 | G4: Project: | H4: Brazonics GC | K4: Period End: | L4: 45291 | S4: p: (781) 272-2899 | U4: Project: | V4: =H4 -> Brazonics GC | Y4: Period End: | Z4: =L4 -> 45291
W5: Brazonics.GC | X5: Brazonics.GC
A6: Contractor's Application for Payment | N6: Work Summary
N7: Cost Code | P7: Description | U7: Scheduled Value | V7: Previous | W7: Current | X7: Total | Y7: % Complete | Z7: Balance to Complete | AA7: 5% Retainage
A8: Change Order Summary | D8: Additions | F8: Deductions | I8: Original Contract Sum | L8: =U37 -> 9374183.4
A9: Total Approved in Prior Months | I9: Net Change by Change Order | L9: =SUM(D14:G14) -> 0 | N9: 010010 | P9: General Requirements | U9: 92409.5 | V9: =X9-W9 -> #VALUE! | W9: #VALUE! | X9: #VALUE! | Y9: =X9/U9 -> #VALUE! | Z9: =U9-X9 -> #VALUE! | AA9: 0 | AD9: #VALUE! | AE9: Total Completed Check to Inv Log
A10: Total Approved this Month | I10: Contract Sum to Date | L10: =L8+L9 -> 9374183.4 | N10: 024000 | P10: Demo | U10: 261545 | V10: =X10-W10 -> #VALUE! | W10: #VALUE! | X10: #VALUE! | Y10: =X10/U10 -> #VALUE! | Z10: =U10-X10 -> #VALUE! | AA10: 0
C11: TOTALS | D11: =SUM(D9:E10) -> 0 | F11: =SUM(F9:G10) -> 0 | I11: Total Completed and Stored | L11: =X37 -> #VALUE! | N11: 030010 | P11: Concrete | U11: 374142.2 | V11: =X11-W11 -> #VALUE! | W11: #VALUE! | X11: #VALUE! | Y11: =X11/U11 -> #VALUE! | Z11: =U11-X11 -> #VALUE! | AA11: 0
A12: Owner's Contingency Assignment | D12: =D11 -> 0 | F12: =F11 -> 0 | I12: 0.05 | J12: Retainage to Date | L12: =AA37 -> 0 | N12: 052000 | P12: Misc. Metals & Structural Steel | U12: 149550 | V12: =X12-W12 -> #VALUE! | W12: #VALUE! | X12: #VALUE! | Y12: =X12/U12 -> #VALUE! | Z12: =U12-X12 -> #VALUE! | AA12: 0
I13: Total Earned Less Retainage | L13: =L11-L12 -> #VALUE! | N13: 100561 | P13: Millwork & Solid Surfaces | U13: 29333 | V13: =X13-W13 -> #VALUE! | W13: #VALUE! | X13: #VALUE! | Y13: =X13/U13 -> #VALUE! | Z13: =U13-X13 -> #VALUE! | AA13: 0
A14: Total Changes to Contract Sum | D14: =D11-D13 -> 0 | F14: =F11-F13 -> 0 | I14: Previous Certificates for Payment | L14: =V37 -> #VALUE! | N14: 075000 | P14: Roofing | U14: 62500 | V14: =X14-W14 -> #VALUE! | W14: #VALUE! | X14: #VALUE! | Y14: =X14/U14 -> #VALUE! | Z14: =U14-X14 -> #VALUE! | AA14: 0
I15: Current Payment Due | L15: =L13-L14 -> #VALUE! | N15: 081000 | P15: Doors, Frames, & Hardware | U15: 116266.4 | V15: =X15-W15 -> #VALUE! | W15: #VALUE! | X15: #VALUE! | Y15: =X15/U15 -> #VALUE! | Z15: =U15-X15 -> #VALUE! | AA15: 0
I16: Balance to Finish, plus Retainage | L16: =L10-L14-L15 -> #VALUE! | N16: 083323 | P16: Overhead Doors | U16: 138177.68 | V16: =X16-W16 -> #VALUE! | W16: #VALUE! | X16: #VALUE! | Y16: =X16/U16 -> #VALUE! | Z16: =U16-X16 -> #VALUE! | AA16: 0
N17: 088100 | P17: Glass Glazing | U17: 40697.41 | V17: =X17-W17 -> #VALUE! | W17: #VALUE! | X17: #VALUE! | Y17: =X17/U17 -> #VALUE! | Z17: =U17-X17 -> #VALUE! | AA17: 0
B18: Contractor's Sworn Statement and Affidavit | H18: Current Payment Due | N18: 092000 | P18: Framing & Drywall | U18: 802775 | V18: =X18-W18 -> #VALUE! | W18: #VALUE! | X18: #VALUE! | Y18: =X18/U18 -> #VALUE! | Z18: =U18-X18 -> #VALUE! | AA18: 0
B19: RJ Kelly Co. Inc affirms to the best of our knowledge and understanding that the Work included in this Application for Payment has been completed approximately to the level of progress indicated and to the detail outlined in the Contract Documents, that all amounts have been paid by RJ Kelly Co. Inc to its first-tier subcontrators as listed, and RJ Kelly Co. Inc is due the amount shown as Current Payment Due. | H19: =L15 -> #VALUE! | N19: 095000 | P19: Ceilings | U19: 168150 | V19: =X19-W19 -> #VALUE! | W19: #VALUE! | X19: #VALUE! | Y19: =X19/U19 -> #VALUE! | Z19: =U19-X19 -> #VALUE! | AA19: 0
N20: 096000 | P20: Flooring | U20: 115271.04 | V20: =X20-W20 -> #VALUE! | W20: #VALUE! | X20: #VALUE! | Y20: =X20/U20 -> #VALUE! | Z20: =U20-X20 -> #VALUE! | AA20: 0
N21: 099000 | P21: Painting | U21: 147165 | V21: =X21-W21 -> #VALUE! | W21: #VALUE! | X21: #VALUE! | Y21: =X21/U21 -> #VALUE! | Z21: =U21-X21 -> #VALUE! | AA21: 0
H22: Amount Authorized for Payment by Owner | N22: 130000 | P22: Specialties - Bathrooms | U22: 42347.84 | V22: =X22-W22 -> #VALUE! | W22: #VALUE! | X22: #VALUE! | Y22: =X22/U22 -> #VALUE! | Z22: =U22-X22 -> #VALUE! | AA22: 0 | AE22: 125
H23: =H19 -> #VALUE! | N23: 110010 | P23: Equipment | U23: 114014.5 | V23: =X23-W23 -> #VALUE! | W23: #VALUE! | X23: #VALUE! | Y23: =X23/U23 -> #VALUE! | Z23: =U23-X23 -> #VALUE! | AA23: 0 | AE23: 105
N24: 210010 | P24: Fire Suppression | U24: 287800 | V24: =X24-W24 -> #VALUE! | W24: #VALUE! | X24: #VALUE! | Y24: =X24/U24 -> #VALUE! | Z24: =U24-X24 -> #VALUE! | AA24: 0 | AE24: 80
N25: 220010 | P25: Plumbing | U25: 324600 | V25: =X25-W25 -> #VALUE! | W25: #VALUE! | X25: #VALUE! | Y25: =X25/U25 -> #VALUE! | Z25: =U25-X25 -> #VALUE! | AA25: 0 | AE25: 90
B26: By: | H26: By: | N26: 230010 | P26: HVAC & Controls | U26: 1547000 | V26: =X26-W26 -> #VALUE! | W26: #VALUE! | X26: #VALUE! | Y26: =X26/U26 -> #VALUE! | Z26: =U26-X26 -> #VALUE! | AA26: 0 | AE26: 62.5
N27: 260010 | P27: Electrical & Fire Alarm | U27: 1854407 | V27: =X27-W27 -> #VALUE! | W27: #VALUE! | X27: #VALUE! | Y27: =X27/U27 -> #VALUE! | Z27: =U27-X27 -> #VALUE! | AA27: 0
N28: 329000 | P28: Sitework & Fencing | U28: 198912 | V28: =X28-W28 -> #VALUE! | W28: #VALUE! | X28: #VALUE! | Y28: =X28/U28 -> #VALUE! | Z28: =U28-X28 -> #VALUE! | AA28: 0
B29: Doug Malone, VP of Construction, RJ Kelly Co., Inc. | H29: Owner or Owner's Authorized Representative | P29: Subtotal - Contractor Hard Costs | U29: =SUM(U9:U28) -> 6867063.6 | V29: =SUM(V9:V28) -> #VALUE! | W29: =SUM(W9:W28) -> #VALUE! | X29: =SUM(X9:X28) -> #VALUE! | Y29: =X29/U29 -> #VALUE! | Z29: =U29-X29 -> #VALUE! | AA29: =SUBTOTAL(9,AA9:AA28) -> 0
N30: LABOR | P30: GC Mgmt & Labor | U30: 848280 | V30: =X30-W30 -> #VALUE! | W30: #VALUE! | X30: #VALUE! | Y30: =X30/U30 -> #VALUE! | Z30: =U30-X30 -> #VALUE!
N31: 007200 | P31: GC Fee & Overhead | S31: 0.05 | U31: 442178.46 | V31: 43495.73 | W31: =(W29+SUM(W34:W35))*$S$31 -> #VALUE! | X31: =V31+W31 -> #VALUE! | Y31: =X31/U31 -> #VALUE! | Z31: =U31-X31 -> #VALUE!
N32: 007316 | P32: GC Insurance | S32: 0.02 | U32: 176871.39 | V32: 9651.67 | W32: =W29*$S$32 -> #VALUE! | X32: =V32+W32 -> #VALUE! | Y32: =X32/U32 -> #VALUE! | Z32: =U32-X32 -> #VALUE!
N33: 012116 | P33: GC Contingency | U33: =9374183.45-SUM(U29,U30:U32,U34:U35) -> 695765.23 | V33: =X33-W33 -> #VALUE! | W33: #VALUE! | X33: #VALUE! | Y33: =X33/U33 -> #VALUE! | Z33: =U33-X33 -> #VALUE!
N34: 001010 | P34: Architectual & Engineering | U34: 287168 | V34: =X34-W34 -> #VALUE! | W34: #VALUE! | X34: #VALUE! | Y34: =X34/U34 -> #VALUE! | Z34: =U34-X34 -> #VALUE!
N35: 001100 | P35: Building Permit | U35: 56856.8 | V35: =X35-W35 -> #VALUE! | W35: #VALUE! | X35: #VALUE! | Y35: =X35/U35 -> #VALUE! | Z35: =U35-X35 -> #VALUE!
L36: ` | P36: Subtotal - Contractor Soft Costs | U36: =SUM(U30:U35) -> 2507119.9 | V36: =SUM(V30:V35) -> #VALUE! | W36: =SUM(W30:W35) -> #VALUE! | X36: =SUM(X30:X35) -> #VALUE! | Y36: =X36/U36 -> #VALUE! | Z36: =SUM(Z30:Z35) -> #VALUE! | AA36: =SUM(AA30:AA35) -> 0
P37: Total - Contract | U37: =SUM(U29+U36) -> 9374183.4 | V37: =V36+V29 -> #VALUE! | W37: =W36+W29 -> #VALUE! | X37: =X36+X29 -> #VALUE! | Y37: =X37/U37 -> #VALUE! | Z37: =U37-X37 -> #VALUE! | AA37: =AA36+AA29 -> 0
T44: GC Overhead | U44: 587612.58
T45: GC Fee Difference | U45: =442178.46-U31 -> 0 | V45: =SUM(U44:U46) -> 499176.88 | W45: Remaining Budget
T46: GC Insurance Difference | U46: =88435.69-U32 -> -88435.7
U48: 9374183.4 | V48: Confirm amount that has been disclosed?
U49: =U48-U37 -> 0 | V49: Remaining Budget
