Workbook
Name \0: #REF!
Name \A: #REF!
Name \asdf: #REF!
Name \B: #REF!
Name \C: #REF!
Name \d: #REF!
Name \E: #REF!
Name \F: #REF!
Name \Fa: #REF!
Name \G: #REF!
Name \H: #REF!
Name \I: #REF!
Name \K: #REF!
Name \l: #REF!
Name \M: #REF!
Name \n: #REF!
Name \P: #REF!
Name \Q: #REF!
Name \R: #REF!
Name \S: #REF!
Name \T: #REF!
Name \U: #REF!
Name \V: #REF!
Name \W: #REF!
Name \X: #REF!
Name \Y: #REF!
Name \Z: #REF!
Name _: #REF!
Name __________cmp1: #REF!
Name __________cmp1: #REF!
Name __________glf1: #REF!
Name __________glf1: #REF!
Name __________hrh1: #REF!
Name __________hrh1: #REF!
Name __________hrm1: #REF!
Name __________hrm1: #REF!
Name __________kit61: #REF!
Name __________kit61: #REF!
Name __________lbh1: #REF!
Name __________lbh1: #REF!
Name __________lbm1: #REF!
Name __________lbm1: #REF!
Name __________pkh1: #REF!
Name __________pkh1: #REF!
Name __________pkm1: #REF!
Name __________pkm1: #REF!
Name __________rsh1: #REF!
Name __________rsh1: #REF!
Name __________rsm1: #REF!
Name __________rsm1: #REF!
Name __________rst1: #REF!
Name __________rst1: #REF!
Name __________rst2: #REF!
Name __________rst2: #REF!
Name __________rst3: #REF!
Name __________rst3: #REF!
Name __________rst4: #REF!
Name __________rst4: #REF!
Name __________rt1: #REF!
Name __________rt1: #REF!

Sheet INTERNAL-->

Sheet DRIVER
B7: GENERAL - INTERNAL: | D7: Notes
B9: Property: | C9: PROPERTY A
B10: Tenant Name: | C10: TENANT X
B11: Unit #: | C11: n/a
B12: SF: | C12: 75000
B13: Improvement Allowance Amount: | C13: 750000 | D13: FROM TENANT IMPROVEMENTS AGREEMENT
B14: Other Allowance Amount: | D14: FROM TENANT IMPROVEMENTS AGREEMENT/OTHER
B15: Supervisory Fee: | C15: 0.01 | D15: FROM TENANT IMPROVEMENTS AGREEMENT
B16: Supervisory Fee Cap:
B17: Supervisory Fee Pool: | C17: IMPROVEMENTS | D17: 1% on total costs of Tenant Improvement or amount of Allowance
B18: Retainage: | C18: 0.05 | D18: FROM TENANT IMPROVEMENTS AGREEMENT
B19: Uniform Improvement Clause: | D19: Yes/No
B20: Funding Structure: | C20: Pari passu | D20: (i.e. LL $ first, Tenant $ first, pari passu) - should maybe make drop down
B23: DEADLINSE & APPROVALS | D23: Notes
B26: Space Plan Deadline:
B27: Plans and Specs Deadline:
B28: LL Approved Tenant's Architect:
B29: LL Approved Tenant Contractor:
B33: EXCLUDED USES
B35: FROM TENANT IMPROVEMENTS AGREEMENT
B42: APPROVED COSTS:
B44: FROM TENANT IMPROVEMENTS AGREEMENT
B51: TENANT WORK INFO: | D51: Notes
B53: Total Original Project Buget: | C53: ='BUDGET & TRACKER'!$F$31 -> 905000 | D53: FROM TENANT PROJECT BUDGET, consistent with Plans & Specs
B54: Approved LL Change Orders: | C54: ='BUDGET & TRACKER'!#REF! -> #REF! | D54: FROM TENANT, "Changes to Plans & Specs:
B55: Total Current Project Budget: | C55: ='BUDGET & TRACKER'!$H$31 -> 905000 | D55: Original + Approved Change Orders
B59: TENANT CONTACTS:
B61: NAME | C61: COMPANY | D61: POSITION | E61: EMAIL | F61: PHONE #

Sheet TIA TRACKER
B7: GENERAL:
B9: Property: | C9: =DRIVER!C9 -> PROPERTY A
B10: Tenant Name: | C10: =DRIVER!C10 -> TENANT X
B11: Unit #: | C11: =DRIVER!C11 -> n/a
B12: SF: | C12: =DRIVER!C12 -> 75000
B14: FUNDING INFO
D16: NOTES:
B18: Total TIA Amount: | C18: =DRIVER!C13 -> 750000
B19: less: Supervisory Fee: | C19: =-IF(DRIVER!$C$17="IMPROVEMENTS", ('BUDGET & TRACKER'!$H$29+'BUDGET & TRACKER'!$H$16)*DRIVER!$C$15, MIN(($C$18)*DRIVER!$C$15, DRIVER!$C$13 * DRIVER!$C$15)) -> -9050
C20: =SUM(C18:C19) -> 740950
B21: less: Retainage: | C21: =-C20*DRIVER!$C$18 -> -37047.5
B22: Total Release Pre-Retainage: | C22: =SUM(C20:C21) -> 703902.5
B23: Total Retainage Held: | C23: =-C21 -> 37047.5
B27: TENANT ALLOWANCE REQUESTS
B29: REQUEST # | C29: REQUEST DATE | D29: TOTAL | E29: SUPERVISORY | F29: RETAINAGE | G29: NET | H29: RUNNING NET | I29: PAYMENTS | J29: NOTES:
B31: REQUEST #1 | H31: =G31 -> 0 | I31: =SUMIFS($C$49:$C$59, $A$49:$A$59, "<=" & A31) -> 0
B32: REQUEST #2 | H32: =SUM(G$31:G32) -> 0 | I32: =SUMIFS($C$49:$C$59, $A$49:$A$59, "<=" & A32) -> 0
B33: REQUEST #3 | H33: =SUM(G$31:G33) -> 0 | I33: =SUMIFS($C$49:$C$59, $A$49:$A$59, "<=" & A33) -> 0
B34: REQUEST #4 | H34: =SUM(G$31:G34) -> 0 | I34: =SUMIFS($C$49:$C$59, $A$49:$A$59, "<=" & A34) -> 0
B35: REQUEST #5 | H35: =SUM(G$31:G35) -> 0 | I35: =SUMIFS($C$49:$C$59, $A$49:$A$59, "<=" & A35) -> 0
B36: REQUEST #6 | H36: =SUM(G$31:G36) -> 0 | I36: =SUMIFS($C$49:$C$59, $A$49:$A$59, "<=" & A36) -> 0
B37: REQUEST #7 | H37: =SUM(G$31:G37) -> 0 | I37: =SUMIFS($C$49:$C$59, $A$49:$A$59, "<=" & A37) -> 0
B38: REQUEST #8 | H38: =SUM(G$31:G38) -> 0 | I38: =SUMIFS($C$49:$C$59, $A$49:$A$59, "<=" & A38) -> 0
B39: REQUEST #9 | H39: =SUM(G$31:G39) -> 0 | I39: =SUMIFS($C$49:$C$59, $A$49:$A$59, "<=" & A39) -> 0
B40: REQUEST #10 | H40: =SUM(G$31:G40) -> 0 | I40: =SUMIFS($C$49:$C$59, $A$49:$A$59, "<=" & A40) -> 0
B42: TOTAL | D42: =SUM(D31:D41) -> 0 | E42: =SUM(E31:E41) -> 0 | F42: =SUM(F31:F41) -> 0 | G42: =SUM(G31:G41) -> 0
B45: DISBURSEMENTS
B47: REQUEST # | C47: TOTAL | D47: PAYMENT DATE
B60: TOTAL | C60: =SUM(C49:C59) -> 0

Sheet TENANT-->

Sheet BUDGET & TRACKER
C1: RJ Kelly Co., Inc. | E1: Property: | F1: =DRIVER!C9 -> PROPERTY A
C2: 55 Cambridge Street | E2: Tenant: | F2: =DRIVER!C10 -> TENANT X
C3: Burlington, MA 01803 | E3: SF: | F3: =DRIVER!C12 -> 75000
C4: p: (781) 272-2899 | E4: Funding: | F4: =DRIVER!C20 -> Pari passu | P4: =_xlfn.IFNA(INDEX(INVOICES!$B$4:$C$1048576,MATCH('BUDGET & TRACKER'!P$8,INVOICES!$B$4:$B$1048576,0),2)," ") | Q4: =_xlfn.IFNA(INDEX(INVOICES!$B$4:$C$1048576,MATCH('BUDGET & TRACKER'!Q$8,INVOICES!$B$4:$B$1048576,0),2)," ") | R4: =_xlfn.IFNA(INDEX(INVOICES!$B$4:$C$1048576,MATCH('BUDGET & TRACKER'!R$8,INVOICES!$B$4:$B$1048576,0),2)," ") | S4: =_xlfn.IFNA(INDEX(INVOICES!$B$4:$C$1048576,MATCH('BUDGET & TRACKER'!S$8,INVOICES!$B$4:$B$1048576,0),2)," ")
I6: REQUEST DATE: | J6: =_xlfn.IFNA(INDEX(INVOICES!$B$4:$C$1048576,MATCH('BUDGET & TRACKER'!J$8,INVOICES!$B$4:$B$1048576,0),2)," ") -> 0 | K6: =_xlfn.IFNA(INDEX(INVOICES!$B$4:$C$1048576,MATCH('BUDGET & TRACKER'!K$8,INVOICES!$B$4:$B$1048576,0),2)," ") -> 0 | L6: =_xlfn.IFNA(INDEX(INVOICES!$B$4:$C$1048576,MATCH('BUDGET & TRACKER'!L$8,INVOICES!$B$4:$B$1048576,0),2)," ") -> 0 | M6: =_xlfn.IFNA(INDEX(INVOICES!$B$4:$C$1048576,MATCH('BUDGET & TRACKER'!M$8,INVOICES!$B$4:$B$1048576,0),2)," ") -> 0 | N6: =_xlfn.IFNA(INDEX(INVOICES!$B$4:$C$1048576,MATCH('BUDGET & TRACKER'!N$8,INVOICES!$B$4:$B$1048576,0),2)," ") | O6: =_xlfn.IFNA(INDEX(INVOICES!$B$4:$C$1048576,MATCH('BUDGET & TRACKER'!O$8,INVOICES!$B$4:$B$1048576,0),2)," ") | P6: =_xlfn.IFNA(INDEX(INVOICES!$B$4:$C$1048576,MATCH('BUDGET & TRACKER'!P$8,INVOICES!$B$4:$B$1048576,0),2)," ") | Q6: =_xlfn.IFNA(INDEX(INVOICES!$B$4:$C$1048576,MATCH('BUDGET & TRACKER'!Q$8,INVOICES!$B$4:$B$1048576,0),2)," ") | ... S6: =_xlfn.IFNA(INDEX(INVOICES!$B$4:$C$1048576,MATCH('BUDGET & TRACKER'!S$8,INVOICES!$B$4:$B$1048576,0),2)," ")
C8: DESCRIPTION | F8: ORIGINAL BUDGET | G8: APPROVED CHANGES | H8: CURRENT BUDGET | J8: REQUEST #1 | K8: REQUEST #2 | L8: REQUEST #3 | M8: REQUEST #4 | N8: REQUEST #5 | O8: REQUEST #6 | P8: REQUEST #7 | Q8: REQUEST #8 | R8: REQUEST #9 | S8: REQUEST #10 | T8: COSTS TO DATE | U8: REMAINING BUDGET
B11: A&E, SOFT COSTS | C11: Architectual & Engineering | F11: 15000 | H11: =F11+G11 -> 15000 | J11: =SUMIFS(INVOICES!$H$6:$H$1048576,INVOICES!$B$6:$B$1048576,'BUDGET & TRACKER'!J$8,INVOICES!$E$6:$E$1048576,'BUDGET & TRACKER'!$C11) -> 0 | K11: =SUMIFS(INVOICES!$H$6:$H$1048576,INVOICES!$B$6:$B$1048576,'BUDGET & TRACKER'!K$8,INVOICES!$E$6:$E$1048576,'BUDGET & TRACKER'!$C11) -> 0 | L11: =SUMIFS(INVOICES!$H$6:$H$1048576,INVOICES!$B$6:$B$1048576,'BUDGET & TRACKER'!L$8,INVOICES!$E$6:$E$1048576,'BUDGET & TRACKER'!$C11) -> 0 | M11: =SUMIFS(INVOICES!$H$6:$H$1048576,INVOICES!$B$6:$B$1048576,'BUDGET & TRACKER'!M$8,INVOICES!$E$6:$E$1048576,'BUDGET & TRACKER'!$C11) -> 0 | N11: =SUMIFS(INVOICES!$H$6:$H$1048576,INVOICES!$B$6:$B$1048576,'BUDGET & TRACKER'!N$8,INVOICES!$E$6:$E$1048576,'BUDGET & TRACKER'!$C11) -> 0 | O11: =SUMIFS(INVOICES!$H$6:$H$1048576,INVOICES!$B$6:$B$1048576,'BUDGET & TRACKER'!O$8,INVOICES!$E$6:$E$1048576,'BUDGET & TRACKER'!$C11) -> 0 | P11: =SUMIFS(INVOICES!$H$6:$H$1048576,INVOICES!$B$6:$B$1048576,'BUDGET & TRACKER'!P$8,INVOICES!$E$6:$E$1048576,'BUDGET & TRACKER'!$C11) -> 0 | Q11: =SUMIFS(INVOICES!$H$6:$H$1048576,INVOICES!$B$6:$B$1048576,'BUDGET & TRACKER'!Q$8,INVOICES!$E$6:$E$1048576,'BUDGET & TRACKER'!$C11) -> 0 | ... S11: =SUMIFS(INVOICES!$H$6:$H$1048576,INVOICES!$B$6:$B$1048576,'BUDGET & TRACKER'!S$8,INVOICES!$E$6:$E$1048576,'BUDGET & TRACKER'!$C11) -> 0 | T11: =SUM(J11:S11) -> 0 | U11: =H11-T11 -> 15000
C12: Building Permit & Fees | F12: 10000 | H12: =F12+G12 -> 10000 | J12: =SUMIFS(INVOICES!$H$6:$H$1048576,INVOICES!$B$6:$B$1048576,'BUDGET & TRACKER'!J$8,INVOICES!$E$6:$E$1048576,'BUDGET & TRACKER'!$C12) -> 0 | K12: =SUMIFS(INVOICES!$H$6:$H$1048576,INVOICES!$B$6:$B$1048576,'BUDGET & TRACKER'!K$8,INVOICES!$E$6:$E$1048576,'BUDGET & TRACKER'!$C12) -> 0 | L12: =SUMIFS(INVOICES!$H$6:$H$1048576,INVOICES!$B$6:$B$1048576,'BUDGET & TRACKER'!L$8,INVOICES!$E$6:$E$1048576,'BUDGET & TRACKER'!$C12) -> 0 | M12: =SUMIFS(INVOICES!$H$6:$H$1048576,INVOICES!$B$6:$B$1048576,'BUDGET & TRACKER'!M$8,INVOICES!$E$6:$E$1048576,'BUDGET & TRACKER'!$C12) -> 0 | N12: =SUMIFS(INVOICES!$H$6:$H$1048576,INVOICES!$B$6:$B$1048576,'BUDGET & TRACKER'!N$8,INVOICES!$E$6:$E$1048576,'BUDGET & TRACKER'!$C12) -> 0 | O12: =SUMIFS(INVOICES!$H$6:$H$1048576,INVOICES!$B$6:$B$1048576,'BUDGET & TRACKER'!O$8,INVOICES!$E$6:$E$1048576,'BUDGET & TRACKER'!$C12) -> 0 | P12: =SUMIFS(INVOICES!$H$6:$H$1048576,INVOICES!$B$6:$B$1048576,'BUDGET & TRACKER'!P$8,INVOICES!$E$6:$E$1048576,'BUDGET & TRACKER'!$C12) -> 0 | Q12: =SUMIFS(INVOICES!$H$6:$H$1048576,INVOICES!$B$6:$B$1048576,'BUDGET & TRACKER'!Q$8,INVOICES!$E$6:$E$1048576,'BUDGET & TRACKER'!$C12) -> 0 | ... S12: =SUMIFS(INVOICES!$H$6:$H$1048576,INVOICES!$B$6:$B$1048576,'BUDGET & TRACKER'!S$8,INVOICES!$E$6:$E$1048576,'BUDGET & TRACKER'!$C12) -> 0 | T12: =SUM(J12:S12) -> 0 | U12: =H12-T12 -> 10000
C13: Legal & Admin | F13: 7500 | H13: =F13+G13 -> 7500 | J13: =SUMIFS(INVOICES!$H$6:$H$1048576,INVOICES!$B$6:$B$1048576,'BUDGET & TRACKER'!J$8,INVOICES!$E$6:$E$1048576,'BUDGET & TRACKER'!$C13) -> 0 | K13: =SUMIFS(INVOICES!$H$6:$H$1048576,INVOICES!$B$6:$B$1048576,'BUDGET & TRACKER'!K$8,INVOICES!$E$6:$E$1048576,'BUDGET & TRACKER'!$C13) -> 0 | L13: =SUMIFS(INVOICES!$H$6:$H$1048576,INVOICES!$B$6:$B$1048576,'BUDGET & TRACKER'!L$8,INVOICES!$E$6:$E$1048576,'BUDGET & TRACKER'!$C13) -> 0 | M13: =SUMIFS(INVOICES!$H$6:$H$1048576,INVOICES!$B$6:$B$1048576,'BUDGET & TRACKER'!M$8,INVOICES!$E$6:$E$1048576,'BUDGET & TRACKER'!$C13) -> 0 | N13: =SUMIFS(INVOICES!$H$6:$H$1048576,INVOICES!$B$6:$B$1048576,'BUDGET & TRACKER'!N$8,INVOICES!$E$6:$E$1048576,'BUDGET & TRACKER'!$C13) -> 0 | O13: =SUMIFS(INVOICES!$H$6:$H$1048576,INVOICES!$B$6:$B$1048576,'BUDGET & TRACKER'!O$8,INVOICES!$E$6:$E$1048576,'BUDGET & TRACKER'!$C13) -> 0 | P13: =SUMIFS(INVOICES!$H$6:$H$1048576,INVOICES!$B$6:$B$1048576,'BUDGET & TRACKER'!P$8,INVOICES!$E$6:$E$1048576,'BUDGET & TRACKER'!$C13) -> 0 | Q13: =SUMIFS(INVOICES!$H$6:$H$1048576,INVOICES!$B$6:$B$1048576,'BUDGET & TRACKER'!Q$8,INVOICES!$E$6:$E$1048576,'BUDGET & TRACKER'!$C13) -> 0 | ... S13: =SUMIFS(INVOICES!$H$6:$H$1048576,INVOICES!$B$6:$B$1048576,'BUDGET & TRACKER'!S$8,INVOICES!$E$6:$E$1048576,'BUDGET & TRACKER'!$C13) -> 0 | T13: =SUM(J13:S13) -> 0 | U13: =H13-T13 -> 7500
C14: Construction Manager | F14: 20000 | H14: =F14+G14 -> 20000 | J14: =SUMIFS(INVOICES!$H$6:$H$1048576,INVOICES!$B$6:$B$1048576,'BUDGET & TRACKER'!J$8,INVOICES!$E$6:$E$1048576,'BUDGET & TRACKER'!$C14) -> 0 | K14: =SUMIFS(INVOICES!$H$6:$H$1048576,INVOICES!$B$6:$B$1048576,'BUDGET & TRACKER'!K$8,INVOICES!$E$6:$E$1048576,'BUDGET & TRACKER'!$C14) -> 0 | L14: =SUMIFS(INVOICES!$H$6:$H$1048576,INVOICES!$B$6:$B$1048576,'BUDGET & TRACKER'!L$8,INVOICES!$E$6:$E$1048576,'BUDGET & TRACKER'!$C14) -> 0 | M14: =SUMIFS(INVOICES!$H$6:$H$1048576,INVOICES!$B$6:$B$1048576,'BUDGET & TRACKER'!M$8,INVOICES!$E$6:$E$1048576,'BUDGET & TRACKER'!$C14) -> 0 | N14: =SUMIFS(INVOICES!$H$6:$H$1048576,INVOICES!$B$6:$B$1048576,'BUDGET & TRACKER'!N$8,INVOICES!$E$6:$E$1048576,'BUDGET & TRACKER'!$C14) -> 0 | O14: =SUMIFS(INVOICES!$H$6:$H$1048576,INVOICES!$B$6:$B$1048576,'BUDGET & TRACKER'!O$8,INVOICES!$E$6:$E$1048576,'BUDGET & TRACKER'!$C14) -> 0 | P14: =SUMIFS(INVOICES!$H$6:$H$1048576,INVOICES!$B$6:$B$1048576,'BUDGET & TRACKER'!P$8,INVOICES!$E$6:$E$1048576,'BUDGET & TRACKER'!$C14) -> 0 | Q14: =SUMIFS(INVOICES!$H$6:$H$1048576,INVOICES!$B$6:$B$1048576,'BUDGET & TRACKER'!Q$8,INVOICES!$E$6:$E$1048576,'BUDGET & TRACKER'!$C14) -> 0 | ... S14: =SUMIFS(INVOICES!$H$6:$H$1048576,INVOICES!$B$6:$B$1048576,'BUDGET & TRACKER'!S$8,INVOICES!$E$6:$E$1048576,'BUDGET & TRACKER'!$C14) -> 0 | T14: =SUM(J14:S14) -> 0 | U14: =H14-T14 -> 20000
H15: =F15+G15 -> 0 | J15: =SUMIFS(INVOICES!$H$6:$H$1048576,INVOICES!$B$6:$B$1048576,'BUDGET & TRACKER'!J$8,INVOICES!$E$6:$E$1048576,'BUDGET & TRACKER'!$C15) -> 0 | K15: =SUMIFS(INVOICES!$H$6:$H$1048576,INVOICES!$B$6:$B$1048576,'BUDGET & TRACKER'!K$8,INVOICES!$E$6:$E$1048576,'BUDGET & TRACKER'!$C15) -> 0 | L15: =SUMIFS(INVOICES!$H$6:$H$1048576,INVOICES!$B$6:$B$1048576,'BUDGET & TRACKER'!L$8,INVOICES!$E$6:$E$1048576,'BUDGET & TRACKER'!$C15) -> 0 | M15: =SUMIFS(INVOICES!$H$6:$H$1048576,INVOICES!$B$6:$B$1048576,'BUDGET & TRACKER'!M$8,INVOICES!$E$6:$E$1048576,'BUDGET & TRACKER'!$C15) -> 0 | N15: =SUMIFS(INVOICES!$H$6:$H$1048576,INVOICES!$B$6:$B$1048576,'BUDGET & TRACKER'!N$8,INVOICES!$E$6:$E$1048576,'BUDGET & TRACKER'!$C15) -> 0 | O15: =SUMIFS(INVOICES!$H$6:$H$1048576,INVOICES!$B$6:$B$1048576,'BUDGET & TRACKER'!O$8,INVOICES!$E$6:$E$1048576,'BUDGET & TRACKER'!$C15) -> 0 | P15: =SUMIFS(INVOICES!$H$6:$H$1048576,INVOICES!$B$6:$B$1048576,'BUDGET & TRACKER'!P$8,INVOICES!$E$6:$E$1048576,'BUDGET & TRACKER'!$C15) -> 0 | Q15: =SUMIFS(INVOICES!$H$6:$H$1048576,INVOICES!$B$6:$B$1048576,'BUDGET & TRACKER'!Q$8,INVOICES!$E$6:$E$1048576,'BUDGET & TRACKER'!$C15) -> 0 | ... S15: =SUMIFS(INVOICES!$H$6:$H$1048576,INVOICES!$B$6:$B$1048576,'BUDGET & TRACKER'!S$8,INVOICES!$E$6:$E$1048576,'BUDGET & TRACKER'!$C15) -> 0 | T15: =SUM(J15:S15) -> 0 | U15: =H15-T15 -> 0
B16: A&E, SOFT COSTS TOTAL | F16: =SUM(F11:F15) -> 52500 | G16: =SUM(G11:G15) -> 0 | H16: =SUM(H11:H15) -> 52500 | J16: =SUM(J11:J15) -> 0 | K16: =SUM(K11:K15) -> 0 | L16: =SUM(L11:L15) -> 0 | M16: =SUM(M11:M15) -> 0 | N16: =SUM(N11:N15) -> 0 | O16: =SUM(O11:O15) -> 0 | P16: =SUM(P11:P15) -> 0 | S16: =SUM(S11:S15) -> 0 | T16: =SUM(T11:T15) -> 0 | U16: =SUM(U11:U15) -> 52500
B18: GC, HARD COSTS | C18: GC Contract Costs | F18: 725000 | H18: =F18+G18 -> 725000 | J18: =SUMIFS(INVOICES!$H$6:$H$1048576,INVOICES!$B$6:$B$1048576,'BUDGET & TRACKER'!J$8,INVOICES!$E$6:$E$1048576,'BUDGET & TRACKER'!$C18) -> 40000 | K18: =SUMIFS(INVOICES!$H$6:$H$1048576,INVOICES!$B$6:$B$1048576,'BUDGET & TRACKER'!K$8,INVOICES!$E$6:$E$1048576,'BUDGET & TRACKER'!$C18) -> 40000 | L18: =SUMIFS(INVOICES!$H$6:$H$1048576,INVOICES!$B$6:$B$1048576,'BUDGET & TRACKER'!L$8,INVOICES!$E$6:$E$1048576,'BUDGET & TRACKER'!$C18) -> 40000 | M18: =SUMIFS(INVOICES!$H$6:$H$1048576,INVOICES!$B$6:$B$1048576,'BUDGET & TRACKER'!M$8,INVOICES!$E$6:$E$1048576,'BUDGET & TRACKER'!$C18) -> 300000 | N18: =SUMIFS(INVOICES!$H$6:$H$1048576,INVOICES!$B$6:$B$1048576,'BUDGET & TRACKER'!N$8,INVOICES!$E$6:$E$1048576,'BUDGET & TRACKER'!$C18) -> 0 | O18: =SUMIFS(INVOICES!$H$6:$H$1048576,INVOICES!$B$6:$B$1048576,'BUDGET & TRACKER'!O$8,INVOICES!$E$6:$E$1048576,'BUDGET & TRACKER'!$C18) -> 0 | P18: =SUMIFS(INVOICES!$H$6:$H$1048576,INVOICES!$B$6:$B$1048576,'BUDGET & TRACKER'!P$8,INVOICES!$E$6:$E$1048576,'BUDGET & TRACKER'!$C18) -> 0 | Q18: =SUMIFS(INVOICES!$H$6:$H$1048576,INVOICES!$B$6:$B$1048576,'BUDGET & TRACKER'!Q$8,INVOICES!$E$6:$E$1048576,'BUDGET & TRACKER'!$C18) -> 0 | ... S18: =SUMIFS(INVOICES!$H$6:$H$1048576,INVOICES!$B$6:$B$1048576,'BUDGET & TRACKER'!S$8,INVOICES!$E$6:$E$1048576,'BUDGET & TRACKER'!$C18) -> 0 | T18: =SUM(J18:S18) -> 420000 | U18: =H18-T18 -> 305000
C19: Tenant-Managed Direct Costs | F19: 85000 | H19: =F19+G19 -> 85000 | J19: =SUMIFS(INVOICES!$H$6:$H$1048576,INVOICES!$B$6:$B$1048576,'BUDGET & TRACKER'!J$8,INVOICES!$E$6:$E$1048576,'BUDGET & TRACKER'!$C19) -> 0 | K19: =SUMIFS(INVOICES!$H$6:$H$1048576,INVOICES!$B$6:$B$1048576,'BUDGET & TRACKER'!K$8,INVOICES!$E$6:$E$1048576,'BUDGET & TRACKER'!$C19) -> 0 | L19: =SUMIFS(INVOICES!$H$6:$H$1048576,INVOICES!$B$6:$B$1048576,'BUDGET & TRACKER'!L$8,INVOICES!$E$6:$E$1048576,'BUDGET & TRACKER'!$C19) -> 0 | M19: =SUMIFS(INVOICES!$H$6:$H$1048576,INVOICES!$B$6:$B$1048576,'BUDGET & TRACKER'!M$8,INVOICES!$E$6:$E$1048576,'BUDGET & TRACKER'!$C19) -> 0 | N19: =SUMIFS(INVOICES!$H$6:$H$1048576,INVOICES!$B$6:$B$1048576,'BUDGET & TRACKER'!N$8,INVOICES!$E$6:$E$1048576,'BUDGET & TRACKER'!$C19) -> 0 | O19: =SUMIFS(INVOICES!$H$6:$H$1048576,INVOICES!$B$6:$B$1048576,'BUDGET & TRACKER'!O$8,INVOICES!$E$6:$E$1048576,'BUDGET & TRACKER'!$C19) -> 0 | P19: =SUMIFS(INVOICES!$H$6:$H$1048576,INVOICES!$B$6:$B$1048576,'BUDGET & TRACKER'!P$8,INVOICES!$E$6:$E$1048576,'BUDGET & TRACKER'!$C19) -> 0 | Q19: =SUMIFS(INVOICES!$H$6:$H$1048576,INVOICES!$B$6:$B$1048576,'BUDGET & TRACKER'!Q$8,INVOICES!$E$6:$E$1048576,'BUDGET & TRACKER'!$C19) -> 0 | ... S19: =SUMIFS(INVOICES!$H$6:$H$1048576,INVOICES!$B$6:$B$1048576,'BUDGET & TRACKER'!S$8,INVOICES!$E$6:$E$1048576,'BUDGET & TRACKER'!$C19) -> 0 | T19: =SUM(J19:S19) -> 0 | U19: =H19-T19 -> 85000
C20: FF&E / Personal Property | F20: 32500 | H20: =F20+G20 -> 32500 | J20: =SUMIFS(INVOICES!$H$6:$H$1048576,INVOICES!$B$6:$B$1048576,'BUDGET & TRACKER'!J$8,INVOICES!$E$6:$E$1048576,'BUDGET & TRACKER'!$C20) -> 0 | K20: =SUMIFS(INVOICES!$H$6:$H$1048576,INVOICES!$B$6:$B$1048576,'BUDGET & TRACKER'!K$8,INVOICES!$E$6:$E$1048576,'BUDGET & TRACKER'!$C20) -> 0 | L20: =SUMIFS(INVOICES!$H$6:$H$1048576,INVOICES!$B$6:$B$1048576,'BUDGET & TRACKER'!L$8,INVOICES!$E$6:$E$1048576,'BUDGET & TRACKER'!$C20) -> 0 | M20: =SUMIFS(INVOICES!$H$6:$H$1048576,INVOICES!$B$6:$B$1048576,'BUDGET & TRACKER'!M$8,INVOICES!$E$6:$E$1048576,'BUDGET & TRACKER'!$C20) -> 0 | N20: =SUMIFS(INVOICES!$H$6:$H$1048576,INVOICES!$B$6:$B$1048576,'BUDGET & TRACKER'!N$8,INVOICES!$E$6:$E$1048576,'BUDGET & TRACKER'!$C20) -> 0 | O20: =SUMIFS(INVOICES!$H$6:$H$1048576,INVOICES!$B$6:$B$1048576,'BUDGET & TRACKER'!O$8,INVOICES!$E$6:$E$1048576,'BUDGET & TRACKER'!$C20) -> 0 | P20: =SUMIFS(INVOICES!$H$6:$H$1048576,INVOICES!$B$6:$B$1048576,'BUDGET & TRACKER'!P$8,INVOICES!$E$6:$E$1048576,'BUDGET & TRACKER'!$C20) -> 0 | Q20: =SUMIFS(INVOICES!$H$6:$H$1048576,INVOICES!$B$6:$B$1048576,'BUDGET & TRACKER'!Q$8,INVOICES!$E$6:$E$1048576,'BUDGET & TRACKER'!$C20) -> 0 | ... S20: =SUMIFS(INVOICES!$H$6:$H$1048576,INVOICES!$B$6:$B$1048576,'BUDGET & TRACKER'!S$8,INVOICES!$E$6:$E$1048576,'BUDGET & TRACKER'!$C20) -> 0 | T20: =SUM(J20:S20) -> 0 | U20: =H20-T20 -> 32500
C21: Allowance for Miscellaneous Costs | F21: 10000 | H21: =F21+G21 -> 10000 | J21: =SUMIFS(INVOICES!$H$6:$H$1048576,INVOICES!$B$6:$B$1048576,'BUDGET & TRACKER'!J$8,INVOICES!$E$6:$E$1048576,'BUDGET & TRACKER'!$C21) -> 0 | K21: =SUMIFS(INVOICES!$H$6:$H$1048576,INVOICES!$B$6:$B$1048576,'BUDGET & TRACKER'!K$8,INVOICES!$E$6:$E$1048576,'BUDGET & TRACKER'!$C21) -> 0 | L21: =SUMIFS(INVOICES!$H$6:$H$1048576,INVOICES!$B$6:$B$1048576,'BUDGET & TRACKER'!L$8,INVOICES!$E$6:$E$1048576,'BUDGET & TRACKER'!$C21) -> 0 | M21: =SUMIFS(INVOICES!$H$6:$H$1048576,INVOICES!$B$6:$B$1048576,'BUDGET & TRACKER'!M$8,INVOICES!$E$6:$E$1048576,'BUDGET & TRACKER'!$C21) -> 0 | N21: =SUMIFS(INVOICES!$H$6:$H$1048576,INVOICES!$B$6:$B$1048576,'BUDGET & TRACKER'!N$8,INVOICES!$E$6:$E$1048576,'BUDGET & TRACKER'!$C21) -> 0 | O21: =SUMIFS(INVOICES!$H$6:$H$1048576,INVOICES!$B$6:$B$1048576,'BUDGET & TRACKER'!O$8,INVOICES!$E$6:$E$1048576,'BUDGET & TRACKER'!$C21) -> 0 | P21: =SUMIFS(INVOICES!$H$6:$H$1048576,INVOICES!$B$6:$B$1048576,'BUDGET & TRACKER'!P$8,INVOICES!$E$6:$E$1048576,'BUDGET & TRACKER'!$C21) -> 0 | Q21: =SUMIFS(INVOICES!$H$6:$H$1048576,INVOICES!$B$6:$B$1048576,'BUDGET & TRACKER'!Q$8,INVOICES!$E$6:$E$1048576,'BUDGET & TRACKER'!$C21) -> 0 | ... S21: =SUMIFS(INVOICES!$H$6:$H$1048576,INVOICES!$B$6:$B$1048576,'BUDGET & TRACKER'!S$8,INVOICES!$E$6:$E$1048576,'BUDGET & TRACKER'!$C21) -> 0 | T21: =SUM(J21:S21) -> 0 | U21: =H21-T21 -> 10000
C22: Project Contingency | F22: 0 | H22: =F22+G22 -> 0 | J22: =SUMIFS(INVOICES!$H$6:$H$1048576,INVOICES!$B$6:$B$1048576,'BUDGET & TRACKER'!J$8,INVOICES!$E$6:$E$1048576,'BUDGET & TRACKER'!$C22) -> 0 | K22: =SUMIFS(INVOICES!$H$6:$H$1048576,INVOICES!$B$6:$B$1048576,'BUDGET & TRACKER'!K$8,INVOICES!$E$6:$E$1048576,'BUDGET & TRACKER'!$C22) -> 0 | L22: =SUMIFS(INVOICES!$H$6:$H$1048576,INVOICES!$B$6:$B$1048576,'BUDGET & TRACKER'!L$8,INVOICES!$E$6:$E$1048576,'BUDGET & TRACKER'!$C22) -> 0 | M22: =SUMIFS(INVOICES!$H$6:$H$1048576,INVOICES!$B$6:$B$1048576,'BUDGET & TRACKER'!M$8,INVOICES!$E$6:$E$1048576,'BUDGET & TRACKER'!$C22) -> 0 | N22: =SUMIFS(INVOICES!$H$6:$H$1048576,INVOICES!$B$6:$B$1048576,'BUDGET & TRACKER'!N$8,INVOICES!$E$6:$E$1048576,'BUDGET & TRACKER'!$C22) -> 0 | O22: =SUMIFS(INVOICES!$H$6:$H$1048576,INVOICES!$B$6:$B$1048576,'BUDGET & TRACKER'!O$8,INVOICES!$E$6:$E$1048576,'BUDGET & TRACKER'!$C22) -> 0 | P22: =SUMIFS(INVOICES!$H$6:$H$1048576,INVOICES!$B$6:$B$1048576,'BUDGET & TRACKER'!P$8,INVOICES!$E$6:$E$1048576,'BUDGET & TRACKER'!$C22) -> 0 | Q22: =SUMIFS(INVOICES!$H$6:$H$1048576,INVOICES!$B$6:$B$1048576,'BUDGET & TRACKER'!Q$8,INVOICES!$E$6:$E$1048576,'BUDGET & TRACKER'!$C22) -> 0 | ... S22: =SUMIFS(INVOICES!$H$6:$H$1048576,INVOICES!$B$6:$B$1048576,'BUDGET & TRACKER'!S$8,INVOICES!$E$6:$E$1048576,'BUDGET & TRACKER'!$C22) -> 0 | T22: =SUM(J22:S22) -> 0 | U22: =H22-T22 -> 0
H27: =F27+G27 -> 0 | J27: =SUMIFS(INVOICES!$H$6:$H$1048576,INVOICES!$B$6:$B$1048576,'BUDGET & TRACKER'!J$8,INVOICES!$E$6:$E$1048576,'BUDGET & TRACKER'!$C27) -> 0 | K27: =SUMIFS(INVOICES!$H$6:$H$1048576,INVOICES!$B$6:$B$1048576,'BUDGET & TRACKER'!K$8,INVOICES!$E$6:$E$1048576,'BUDGET & TRACKER'!$C27) -> 0 | L27: =SUMIFS(INVOICES!$H$6:$H$1048576,INVOICES!$B$6:$B$1048576,'BUDGET & TRACKER'!L$8,INVOICES!$E$6:$E$1048576,'BUDGET & TRACKER'!$C27) -> 0 | M27: =SUMIFS(INVOICES!$H$6:$H$1048576,INVOICES!$B$6:$B$1048576,'BUDGET & TRACKER'!M$8,INVOICES!$E$6:$E$1048576,'BUDGET & TRACKER'!$C27) -> 0 | N27: =SUMIFS(INVOICES!$H$6:$H$1048576,INVOICES!$B$6:$B$1048576,'BUDGET & TRACKER'!N$8,INVOICES!$E$6:$E$1048576,'BUDGET & TRACKER'!$C27) -> 0 | O27: =SUMIFS(INVOICES!$H$6:$H$1048576,INVOICES!$B$6:$B$1048576,'BUDGET & TRACKER'!O$8,INVOICES!$E$6:$E$1048576,'BUDGET & TRACKER'!$C27) -> 0 | P27: =SUMIFS(INVOICES!$H$6:$H$1048576,INVOICES!$B$6:$B$1048576,'BUDGET & TRACKER'!P$8,INVOICES!$E$6:$E$1048576,'BUDGET & TRACKER'!$C27) -> 0 | Q27: =SUMIFS(INVOICES!$H$6:$H$1048576,INVOICES!$B$6:$B$1048576,'BUDGET & TRACKER'!Q$8,INVOICES!$E$6:$E$1048576,'BUDGET & TRACKER'!$C27) -> 0 | ... S27: =SUMIFS(INVOICES!$H$6:$H$1048576,INVOICES!$B$6:$B$1048576,'BUDGET & TRACKER'!S$8,INVOICES!$E$6:$E$1048576,'BUDGET & TRACKER'!$C27) -> 0 | T27: =SUM(J27:S27) -> 0 | U27: =H27-T27 -> 0
H28: =F28+G28 -> 0 | J28: =SUMIFS(INVOICES!$H$6:$H$1048576,INVOICES!$B$6:$B$1048576,'BUDGET & TRACKER'!J$8,INVOICES!$E$6:$E$1048576,'BUDGET & TRACKER'!$C28) -> 0 | K28: =SUMIFS(INVOICES!$H$6:$H$1048576,INVOICES!$B$6:$B$1048576,'BUDGET & TRACKER'!K$8,INVOICES!$E$6:$E$1048576,'BUDGET & TRACKER'!$C28) -> 0 | L28: =SUMIFS(INVOICES!$H$6:$H$1048576,INVOICES!$B$6:$B$1048576,'BUDGET & TRACKER'!L$8,INVOICES!$E$6:$E$1048576,'BUDGET & TRACKER'!$C28) -> 0 | M28: =SUMIFS(INVOICES!$H$6:$H$1048576,INVOICES!$B$6:$B$1048576,'BUDGET & TRACKER'!M$8,INVOICES!$E$6:$E$1048576,'BUDGET & TRACKER'!$C28) -> 0 | N28: =SUMIFS(INVOICES!$H$6:$H$1048576,INVOICES!$B$6:$B$1048576,'BUDGET & TRACKER'!N$8,INVOICES!$E$6:$E$1048576,'BUDGET & TRACKER'!$C28) -> 0 | O28: =SUMIFS(INVOICES!$H$6:$H$1048576,INVOICES!$B$6:$B$1048576,'BUDGET & TRACKER'!O$8,INVOICES!$E$6:$E$1048576,'BUDGET & TRACKER'!$C28) -> 0 | P28: =SUMIFS(INVOICES!$H$6:$H$1048576,INVOICES!$B$6:$B$1048576,'BUDGET & TRACKER'!P$8,INVOICES!$E$6:$E$1048576,'BUDGET & TRACKER'!$C28) -> 0 | Q28: =SUMIFS(INVOICES!$H$6:$H$1048576,INVOICES!$B$6:$B$1048576,'BUDGET & TRACKER'!Q$8,INVOICES!$E$6:$E$1048576,'BUDGET & TRACKER'!$C28) -> 0 | ... S28: =SUMIFS(INVOICES!$H$6:$H$1048576,INVOICES!$B$6:$B$1048576,'BUDGET & TRACKER'!S$8,INVOICES!$E$6:$E$1048576,'BUDGET & TRACKER'!$C28) -> 0 | T28: =SUM(J28:S28) -> 0 | U28: =H28-T28 -> 0
B29: GC, HARD COSTS TOTAL | F29: =SUM(F18:F28) -> 852500 | G29: =SUM(G18:G28) -> 0 | H29: =SUM(H18:H28) -> 852500 | J29: =SUM(J18:J28) -> 40000 | K29: =SUM(K18:K28) -> 40000 | L29: =SUM(L18:L28) -> 40000 | M29: =SUM(M18:M28) -> 300000 | N29: =SUM(N18:N28) -> 0 | O29: =SUM(O18:O28) -> 0 | P29: =SUM(P18:P28) -> 0 | Q29: =SUM(Q18:Q28) -> 0 | ... T29: =SUM(T18:T28) -> 420000 | U29: =H29-T29 -> 432500
B31: TOTAL HARD + SOFT COSTS | F31: =F29+F16 -> 905000 | G31: =G29+G16 -> 0 | H31: =H29+H16 -> 905000 | J31: =J29+J16 -> 40000 | K31: =K29+K16 -> 40000 | L31: =L29+L16 -> 40000 | M31: =M29+M16 -> 300000 | N31: =N29+N16 -> 0 | O31: =O29+O16 -> 0 | P31: =P29+P16 -> 0 | Q31: =Q29+Q16 -> 0 | ... T31: =T29+T16 -> 420000 | U31: =H31-T31 -> 485000 | X31: =H31-H36 -> 155000 | Y31: IMPROVEMENT ALLOWANCE EXCESS
H33: TIA AMOUNT | J33: REQUEST #1 | K33: REQUEST #2 | L33: REQUEST #3 | M33: REQUEST #4 | N33: REQUEST #5 | O33: REQUEST #6 | P33: REQUEST #7 | Q33: REQUEST #8 | R33: REQUEST #9 | S33: REQUEST #10 | T33: REQUESTED TO DATE | U33: REMAINING ALLOWANCE | V33: RETAINAGE RELEASE
G36: Gross Total | H36: ='TIA TRACKER'!$C$18 -> 750000 | J36: =IF(DRIVER!$C$20="Pari passu",($H$36/$H$31)*J31,IF(DRIVER!$C$20="Tenant $ First",MAX((J31-($H$31-$H$36)),0),J31)) -> 33149.171 | K36: =IF(DRIVER!$C$20="Pari passu",($H$36/$H$31)*K31,IF(DRIVER!$C$20="Tenant $ First",MAX(((SUM($J31:K31)-SUM($J36:J36))-($H$31-$H$36)),0),K31)) -> 33149.171 | L36: =IF(DRIVER!$C$20="Pari passu",($H$36/$H$31)*L31,IF(DRIVER!$C$20="Tenant $ First",MAX(((SUM($J31:L31)-SUM($J36:K36))-($H$31-$H$36)),0),L31)) -> 33149.171 | M36: =IF(DRIVER!$C$20="Pari passu",($H$36/$H$31)*M31,IF(DRIVER!$C$20="Tenant $ First",MAX(((SUM($J31:M31)-SUM($J36:L36))-($H$31-$H$36)),0),M31)) -> 248618.78 | N36: =IF(DRIVER!$C$20="Pari passu",($H$36/$H$31)*N31,IF(DRIVER!$C$20="Tenant $ First",MAX(((SUM($J31:N31)-SUM($J36:M36))-($H$31-$H$36)),0),N31)) -> 0 | O36: =IF(DRIVER!$C$20="Pari passu",($H$36/$H$31)*O31,IF(DRIVER!$C$20="Tenant $ First",MAX(((SUM($J31:O31)-SUM($J36:N36))-($H$31-$H$36)),0),O31)) -> 0 | P36: =IF(DRIVER!$C$20="Pari passu",($H$36/$H$31)*P31,IF(DRIVER!$C$20="Tenant $ First",MAX(((SUM($J31:P31)-SUM($J36:O36))-($H$31-$H$36)),0),P31)) -> 0 | Q36: =IF(DRIVER!$C$20="Pari passu",($H$36/$H$31)*Q31,IF(DRIVER!$C$20="Tenant $ First",MAX(((SUM($J31:Q31)-SUM($J36:P36))-($H$31-$H$36)),0),Q31)) -> 0 | R36: =IF(DRIVER!$C$20="Pari passu",($H$36/$H$31)*R31,IF(DRIVER!$C$20="Tenant $ First",MAX(((SUM($J31:R31)-SUM($J36:Q36))-($H$31-$H$36)),0),R31)) -> 0 | S36: =IF(DRIVER!$C$20="Pari passu",($H$36/$H$31)*S31,IF(DRIVER!$C$20="Tenant $ First",MAX(((SUM($J31:S31)-SUM($J36:R36))-($H$31-$H$36)),0),S31)) -> 0 | T36: =SUM(J36:S36) -> 348066.3 | U36: =H36-T36 -> 401933.7 | V36: n/a
E37: =DRIVER!C15 -> 0.01 | G37: less: LL Supervisory Fee | H37: ='TIA TRACKER'!$C$19 -> -9050 | J37: =J36*-$E$37 -> -331.49171 | K37: =K36*-$E$37 -> -331.49171 | L37: =L36*-$E$37 -> -331.49171 | M37: =M36*-$E$37 -> -2486.1878 | N37: =N36*-$E$37 -> 0 | O37: =O36*-$E$37 -> 0 | P37: =P36*-$E$37 -> 0 | Q37: =Q36*-$E$37 -> 0 | ... S37: =S36*-$E$37 -> 0 | T37: =SUM(J37:S37) -> -3480.663 | U37: =H37-T37 -> -5569.337 | V37: n/a
E38: =DRIVER!C18 -> 0.05 | G38: less: LL Project Retainage* | H38: ='TIA TRACKER'!$C$21 -> -37047.5 | J38: =J36*-$E$38 -> -1657.4586 | K38: =K36*-$E$38 -> -1657.4586 | L38: =L36*-$E$38 -> -1657.4586 | M38: =M36*-$E$38 -> -12430.939 | N38: =N36*-$E$38 -> 0 | O38: =O36*-$E$38 -> 0 | P38: =P36*-$E$38 -> 0 | Q38: =Q36*-$E$38 -> 0 | ... S38: =S36*-$E$38 -> 0 | T38: =SUM(J38:S38) -> -17403.315 | U38: =H38-T38 -> -19644.185 | V38: =-H38 -> 37047.5
G39: TOTAL DISBURSEMENTS | H39: =SUM(H36:H38) -> 703902.5 | J39: =SUM(J36:J38) -> 31160.221 | K39: =SUM(K36:K38) -> 31160.221 | L39: =SUM(L36:L38) -> 31160.221 | M39: =SUM(M36:M38) -> 233701.66 | N39: =SUM(N36:N38) -> 0 | O39: =SUM(O36:O38) -> 0 | P39: =SUM(P36:P38) -> 0 | Q39: =SUM(Q36:Q38) -> 0 | ... U39: =SUM(U36:U38) -> 376720.18 | V39: =SUM(V38) -> 37047.5
T44: =(T29+T16)=INVOICES!H2 -> TRUE

Sheet INVOICES
H2: =SUM(H6:H1048576) -> 420000 | I2: TOTAL AMOUNT
H3: ='BUDGET & TRACKER'!T44 -> TRUE
B4: REQUEST # | C4: REQUEST DATE | D4: VENDOR | E4: BUDGET CATEGORY | F4: INVOICE # | G4: INVOICE DATE | H4: AMOUNT | I4: NOTES
B6: REQUEST #1 | E6: GC Contract Costs | H6: 40000
B7: REQUEST #2 | E7: GC Contract Costs | H7: 40000
B8: REQUEST #3 | E8: GC Contract Costs | H8: 40000
B9: REQUEST #4 | E9: GC Contract Costs | H9: 300000
B10: REQUEST #1
B11: REQUEST #1
B12: REQUEST #1
B13: REQUEST #1
B14: REQUEST #1
B15: REQUEST #1
B16: REQUEST #1
B17: REQUEST #1
B18: REQUEST #1
B19: REQUEST #1
B20: REQUEST #1
B21: REQUEST #1
... B57: REQUEST #2

Sheet DROPDOWNS
B3: Yes/No | D3: PROPERTY | F3: REQUEST # | H3: BUDGET CATEGORIES | J3: CO STATUS | L3: SUPERVISORY FEE POOL | N3: FUNDING STRUCTURE
B4: Yes | D4: PROPERTY A | F4: REQUEST #1 | H4: {=_xlfn.TOCOL('BUDGET & TRACKER'!C11:C28,3,FALSE)} -> Architectual & Engineering | J4: REQUESTED | L4: ALLOWANCE | N4: Pari passu
B5: No | D5: 16 Delta Drive - (16delta) | F5: REQUEST #2 | H5: Building Permit & Fees | J5: APPROVED | L5: IMPROVEMENTS | N5: Tenant $ First
B6: N/A | D6: 33 Cherry Hill Drive - (33cherry) | F6: REQUEST #3 | H6: Legal & Admin
D7: 35 Cherry Hill Drive - (35cherry) | F7: REQUEST #4 | H7: Construction Manager
D8: 368 Pepsi Road - (368pepsi) | F8: REQUEST #5 | H8: GC Contract Costs
D9: 37 Cherry Hill Road - (37cherry) | F9: REQUEST #6 | H9: Tenant-Managed Direct Costs
D10: 10 Columbia Drive - (10columb) | F10: REQUEST #7 | H10: FF&E / Personal Property
D11: 10 Mall Road - (mallr10) | F11: REQUEST #8 | H11: Allowance for Miscellaneous Costs
D12: 10 State Street - (10state) | F12: REQUEST #9 | H12: Project Contingency
D13: 100 Quannapowitt Parkway - (100_q) | F13: REQUEST #10
D14: 11 Delta Drive - (11delta)
D15: 11 Executive Park - (11exec)
D16: 111 South Bedford - (111sbed)
D17: 12 Executive Drive - (12_exec)
D18: 12 Innovation - (12inno)
D19: 12 Kent Way - (12kent)
D20: 121 Technology Drive - (121tech)
D21: 125 Goddard Memorial Drive - (125_god)
D22: 13 Hampshire Drive - (13hampsh)
D23: 14 Celina Avenue - (14celina)
D24: 15 Continental Boulevard - (15cont)
D25: 15 Guest Street - (15guest)
... D68: Quarry Square - (quarrysq)

Sheet GPT cache
EUP152005: {"hash":"cdc251c4361a0f65d4c1438af9f477d52ffa6111aec7f6b2ad254f09ef5212c0","version":1,"value":"[[\"The formula calculates a value based on two scenarios:\\nIf cell C16 in the DRIVER sheet equals \\\"IMPROVEMENTS\\\", it calculates 1% of the sum of F54 and F18.\\nOtherwise, it returns the lesser of: 1% of the sum of F54 and F18, or the product of cells C13 and C15 from the DRIVER sheet.\"]]"}
MIH352219: {"hash":"4cd55fdadc5ca345e2068cee9f320cf2177d3d26c8bacf8a65ee6ed946eb26c3","version":1,"value":"[[\"=IF(DRIVER!$C$20=\\\"Pari passu\\\",(W57/H57)*T57,IF(DRIVER!$C$20=\\\"Tenant $ First\\\",T57-(H57-W57),T57))\"]]"}
LMV618533: {"hash":"ae797024413f2117d65ceebafcb8e3988113938fafac60c9369ed1310c12f6b2","version":1,"value":"[[\"The formula calculates a share of income based on three possible distribution methods:\\n\\n1. If \\\"Pari passu\\\": Calculates proportional share (H36/H31 ratio multiplied by J31)\\n2. If \\\"Tenant $ First\\\": Takes tenant's share first, then any remainder up to J31\\n3. Otherwise: Returns full amount in J31\"]]"}
CFN618844: {"hash":"6d79715bb8564895bd081f78ea7f53b50fa317bb9b76c43dbf62543f0e27dad6","version":1,"value":"[[\"=IF(OR(J31<0,K31<0),0,IF(SUM(J31:K31)=0,0,K31/SUM(J31:K31)*J36))\"]]"}
CMJ796299: {"hash":"988c268a96024947779f9c22b5d2aad031b76873cdad5b8d90e8944cb33bb57c","version":1,"value":"[[\"=IF(AND(K31>0,K36>0),K36/K31,\\\"\\\")\"]]"}
